{"d":{"12":{"i":"2yAdSSUJmBHFHHbpsq572s","is":"USSD12000112","n":"Mundo Imaginario","a":[{"i":"1TtXnWcUs0FCkaZDPGYHdf","n":"Darell"}],"p":60,"r":"2020-05-22","l":"Sony Music Latin","im":"https://i.scdn.co/image/ab67616d0000b273731dae7ee04a015c88a69cef","ps":[{"i":"37i9dQZF1DWUlCmB8llCTB","n":44,"a":1597377660000,"p":386},{"i":"37i9dQZF1DX57NRq0pf7ea","n":90,"a":1597096980000,"p":97}],"pp":483},"14":{"i":"1Iop545mi48sE8mNNbxEuy","is":"USSD12000114","n":"La Canción de la Efe","a":[{"i":"23wEWD21D4TPYiJugoXmYb","n":"Thalía"}],"p":24,"r":"2020-05-29","l":"Sony Music Latin","im":"https://i.scdn.co/image/ab67616d0000b27382ececa926969e53606b830e","ps":[{"i":"37i9dQZF1DXbLRILp4Jb3D","n":1,"a":1594942275000,"p":312}],"pp":312},"18":{"i":"1OxpEQfqYrwTVdOQyZ3QCl","is":"USSD12000118","n":"Antes Que el Mundo Se Acabe","a":[{"i":"5GcWBUX00IPuWVGMIRK1sS","n":"Residente"}],"p":67,"r":"2020-05-14","l":"Sony Music Latin","im":"https://i.scdn.co/image/ab67616d0000b273b36b24c8a0385c95854b0e90","ps":[{"i":"37i9dQZF1DWUoGbRYcteyC","n":9,"a":1594070804000,"p":1226},{"i":"37i9dQZF1DWYzTSrc7SiSZ","n":35,"a":1596467170000,"p":531},{"i":"37i9dQZF1DWZKpHIbfDI1i","n":1,"a":1596173460000,"p":479},{"i":"37i9dQZF1DX3rgIhQ2x809","n":3,"a":1596468477000,"p":231},{"i":"37i9dQZF1DWTbNM1k24xvE","n":19,"a":1594269550000,"p":76},{"i":"37i9dQZF1DWSq30bHsgNR5","n":33,"a":1596477009000,"p":24},{"i":"37i9dQZF1DXaIfbw6rIKpz","n":48,"a":1593710940000,"p":23}],"pp":2590},"29":{"i":"4M6J054pKRf3ckRXmi4qio","is":"USSD12000129","n":"Diente","a":[{"i":"23wEWD21D4TPYiJugoXmYb","n":"Thalía"}],"p":22,"r":"2020-05-29","l":"Sony Music Latin","im":"https://i.scdn.co/image/ab67616d0000b27382ececa926969e53606b830e","ps":[{"i":"37i9dQZF1DXbLRILp4Jb3D","n":7,"a":1594942275000,"p":294}],"pp":294},"34":{"i":"2cLOSF54zDP52z6ma8mivK","is":"USSD12000134","n":"Lo Que en Ti Veo","a":[{"i":"69UypehHabb68utzfjAVlV","n":"Kany Garcia"},{"i":"4IjHltwoSKbUeZLPeULyDe","n":"Nahuel Pennisi"}],"p":62,"r":"2020-05-28","l":"Sony Music Latin","im":"https://i.scdn.co/image/ab67616d0000b273324e396b64ae89dc238cb992","ps":[{"i":"37i9dQZF1DX09mi3a4Zmox","n":10,"a":1596058224000,"p":1741},{"i":"37i9dQZF1DWUoGbRYcteyC","n":15,"a":1594070804000,"p":1154},{"i":"37i9dQZF1DX4nV8QNjO7nb","n":20,"a":1594271298000,"p":852},{"i":"37i9dQZF1DX3iDTU5OeufK","n":0,"a":1597196258000,"p":197}],"pp":3944},"35":{"i":"05Qmn8QFzBhRNzSvgBP3YF","is":"USSD12000135","n":"Búscame","a":[{"i":"69UypehHabb68utzfjAVlV","n":"Kany Garcia"},{"i":"4vhNDa5ycK0ST968ek7kRr","n":"Carlos Vives"}],"p":50,"r":"2020-05-28","l":"Sony Music Latin","im":"https://i.scdn.co/image/ab67616d0000b273324e396b64ae89dc238cb992","ps":[{"i":"37i9dQZF1DX2lenzaqw2vs","n":5,"a":1593617306000,"p":333}],"pp":333},"43":{"i":"7F1oLjSguGBvqsJLal7Rad","is":"USSD12000143","n":"Titanic","a":[{"i":"69UypehHabb68utzfjAVlV","n":"Kany Garcia"},{"i":"28gNT5KBp7IjEOQoevXf9N","n":"Camilo"}],"p":69,"r":"2020-05-28","l":"Sony Music Latin","im":"https://i.scdn.co/image/ab67616d0000b273324e396b64ae89dc238cb992","ps":[{"i":"37i9dQZF1DX1QnNyJOBQBv","n":45,"a":1596775304000,"p":845},{"i":"37i9dQZF1DX5AVYhCeISA6","n":12,"a":1594069414000,"p":597},{"i":"37i9dQZF1DX1PiujNwN5Yy","n":14,"a":1596467916000,"p":190},{"i":"37i9dQZEVXbMIO7B1pcKUy","n":44,"a":0,"p":82},{"i":"37i9dQZF1DXaIfbw6rIKpz","n":53,"a":1593710940000,"p":22}],"pp":1736},"50":{"i":"7zh0PdIYt6HxXoPvfb30MU","is":"USSD12000150","n":"Recuerdo","a":[{"i":"7slfeZO9LsJbWgpkIoXBUJ","n":"Ricky Martin"},{"i":"0XK6kT7xcZAlcYrNjOgzJe","n":"Carla Morrison"}],"p":69,"r":"2020-05-28","l":"Sony Music Latin","im":"https://i.scdn.co/image/ab67616d0000b273bb5fb5d93f1a1252d043011e","ps":[{"i":"37i9dQZF1DX4yeSNLFx6qI","n":0,"a":1594070578000,"p":1259},{"i":"37i9dQZF1DWUoGbRYcteyC","n":13,"a":1594070804000,"p":1177},{"i":"37i9dQZF1DX1QnNyJOBQBv","n":31,"a":1596775304000,"p":972},{"i":"37i9dQZF1DX4YhSbTs17ha","n":41,"a":1597190182000,"p":754},{"i":"37i9dQZF1DX14fkzxPABaL","n":23,"a":1597079801000,"p":533},{"i":"37i9dQZF1DWSF59R74xaFB","n":3,"a":1597190266000,"p":469},{"i":"37i9dQZF1DWSpF87bP6JSF","n":9,"a":1596835915000,"p":398},{"i":"37i9dQZF1DX3iDTU5OeufK","n":2,"a":1597196258000,"p":193},{"i":"53gsoDSMuaYKyEBa2izvOV","n":53,"a":1596774383000,"p":151},{"i":"37i9dQZF1DXaIfbw6rIKpz","n":37,"a":1593710940000,"p":26}],"pp":5932},"51":{"i":"3NG3wfTRRPiGLxysGXG5RU","is":"USSD12000151","n":"Cae de Una","a":[{"i":"7slfeZO9LsJbWgpkIoXBUJ","n":"Ricky Martin"},{"i":"4QVBYiagIaa6ZGSPMbybpy","n":"Pedro Capó"}],"p":55,"r":"2020-05-28","l":"Sony Music Latin","im":"https://i.scdn.co/image/ab67616d0000b273bb5fb5d93f1a1252d043011e","ps":[{"i":"1vIZxBcvgGHE9HXbQnzXYI","n":38,"a":1596723038000,"p":532}],"pp":532},"53":{"i":"5kQre7o8ky5DXeEPcyaCR1","is":"USSD12000153","n":"Carita de Inocente (feat. Myke Towers) - Remix","a":[{"i":"3MHaV05u0io8fQbZ2XPtlC","n":"Prince Royce"},{"i":"7iK8PXO48WeuP03g8YR51W","n":"Myke Towers"}],"p":83,"r":"2020-06-01","l":"Sony Music Latin","im":"https://i.scdn.co/image/ab67616d0000b2730ff4283736306e4d63308926","ps":[{"i":"37i9dQZF1DX10zKzsJ2jva","n":26,"a":1597377660000,"p":2506},{"i":"37i9dQZF1DXdnGF35OawbN","n":8,"a":1596466213000,"p":1821},{"i":"37i9dQZF1DXaxEKcoCdWHD","n":6,"a":1597054769000,"p":1393},{"i":"37i9dQZF1DX7MTlMMRl0MD","n":4,"a":1595958858000,"p":1275},{"i":"37i9dQZF1DX4oUPBOaEkL6","n":20,"a":1596653218000,"p":1068},{"i":"37i9dQZEVXbNFJfN1Vw8d9","n":10,"a":0,"p":998},{"i":"37i9dQZF1DWZoF06RIo9el","n":48,"a":1596811919000,"p":733},{"i":"1vIZxBcvgGHE9HXbQnzXYI","n":13,"a":1596723038000,"p":683},{"i":"37i9dQZF1DX62RIcEOaBWi","n":17,"a":1593776722000,"p":606},{"i":"37i9dQZF1DX07X8UDWKEwP","n":42,"a":1596772860000,"p":320},{"i":"37i9dQZEVXbMfVLvbaC3bj","n":29,"a":0,"p":301},{"i":"37i9dQZF1DX29qo6meCGNU","n":27,"a":1597377660000,"p":285},{"i":"37i9dQZF1DWZqdNJSufucb","n":4,"a":1597055997000,"p":276},{"i":"37i9dQZF1DX24r38hOT4JG","n":3,"a":1594651644000,"p":249},{"i":"37i9dQZF1DXa6LZpUXhjpy","n":32,"a":1597376596000,"p":98},{"i":"37i9dQZF1DX3fYslUHVGlt","n":15,"a":1596164491000,"p":79}],"pp":12691},"55":{"i":"5EbtodsuLbxrFDH6j5avVS","is":"USSD12000155","n":"El Mismo Aire - con Pablo Alborán","a":[{"i":"28gNT5KBp7IjEOQoevXf9N","n":"Camilo"},{"i":"5M9Bb4adKAgrOFOhc05Y50","n":"Pablo Alborán"}],"p":86,"r":"2020-06-10","l":"Sony Music Latin","im":"https://i.scdn.co/image/ab67616d0000b27320d0a6e2ca32d7efd7d0a655","ps":[{"i":"37i9dQZF1DX10zKzsJ2jva","n":29,"a":1597377660000,"p":2432},{"i":"37i9dQZF1DX5BAPG29mHS8","n":29,"a":1597330282000,"p":1417},{"i":"37i9dQZF1DX1QnNyJOBQBv","n":5,"a":1596775304000,"p":1263},{"i":"37i9dQZF1DX4YhSbTs17ha","n":5,"a":1597190182000,"p":1083},{"i":"37i9dQZF1DX8CTD7HWYPDn","n":15,"a":1597230866000,"p":1060},{"i":"37i9dQZF1DXbbu94YBG7Ye","n":32,"a":1597260236000,"p":1060},{"i":"37i9dQZF1DX4nV8QNjO7nb","n":8,"a":1594271298000,"p":962},{"i":"37i9dQZF1DX3sCT1ItXgNd","n":1,"a":1596561624000,"p":874},{"i":"37i9dQZF1DXclgCwbk0uat","n":33,"a":1597259989000,"p":858},{"i":"37i9dQZEVXbO3qyFxbkOE1","n":27,"a":0,"p":835},{"i":"37i9dQZEVXbNFJfN1Vw8d9","n":37,"a":0,"p":761},{"i":"37i9dQZF1DX5y71ufjoyXC","n":20,"a":1597377660000,"p":758},{"i":"37i9dQZEVXbMMy2roB9myp","n":25,"a":0,"p":701},{"i":"37i9dQZF1DXbvPjXfc8G9S","n":12,"a":1596668677000,"p":665},{"i":"37i9dQZF1DWTPDzakLfYZr","n":1,"a":1597092812000,"p":659},{"i":"37i9dQZEVXbOa2lmxNORXQ","n":17,"a":0,"p":653},{"i":"37i9dQZF1DX62RIcEOaBWi","n":11,"a":1593776722000,"p":644},{"i":"37i9dQZF1DX14fkzxPABaL","n":8,"a":1597079801000,"p":619},{"i":"37i9dQZF1DX5UTavgI6ivn","n":3,"a":1597113081000,"p":594},{"i":"37i9dQZEVXbJfdy5b0KP7W","n":23,"a":0,"p":486},{"i":"37i9dQZF1DX9C8KzGEUKV4","n":27,"a":1597265062000,"p":482},{"i":"37i9dQZF1DWSF59R74xaFB","n":6,"a":1597190266000,"p":455},{"i":"37i9dQZF1DWVOLXBOylBUZ","n":17,"a":1597356952000,"p":446},{"i":"37i9dQZEVXbL0GavIqMTeb","n":30,"a":0,"p":446},{"i":"37i9dQZF1DWTyTiBbDrmml","n":32,"a":1596146520000,"p":366},{"i":"37i9dQZF1DWSpF87bP6JSF","n":20,"a":1596835915000,"p":356},{"i":"37i9dQZF1DWUbj5dNZ89An","n":19,"a":1595590766000,"p":339},{"i":"37i9dQZEVXbLuUZrygauiA","n":31,"a":0,"p":332},{"i":"37i9dQZF1DXbT1642xPu6H","n":32,"a":1597346498000,"p":305},{"i":"37i9dQZEVXbJlM6nvL1nD1","n":20,"a":0,"p":298},{"i":"37i9dQZEVXbKAbrMR8uuf7","n":22,"a":0,"p":276},{"i":"37i9dQZEVXbJajpaXyaKll","n":34,"a":0,"p":252},{"i":"37i9dQZEVXbNOUPGj7tW6T","n":49,"a":0,"p":231},{"i":"37i9dQZEVXbMZAjGMynsQX","n":37,"a":0,"p":229},{"i":"37i9dQZEVXbMJJi3wgRbAy","n":21,"a":0,"p":224},{"i":"37i9dQZEVXbKypXHVwk1f0","n":27,"a":0,"p":209},{"i":"37i9dQZF1DX1PiujNwN5Yy","n":5,"a":1596467916000,"p":208},{"i":"37i9dQZEVXbJs8e2vk15a8","n":24,"a":0,"p":207},{"i":"53gsoDSMuaYKyEBa2izvOV","n":22,"a":1596774383000,"p":206},{"i":"37i9dQZEVXbJqfMFK4d691","n":21,"a":0,"p":203},{"i":"37i9dQZEVXbKrooeK9WSFF","n":28,"a":0,"p":202},{"i":"37i9dQZEVXbN7gfhgaomhA","n":39,"a":0,"p":189},{"i":"37i9dQZEVXbLy5tBFyQvd4","n":44,"a":0,"p":153},{"i":"37i9dQZF1DWWqmEAq7L8jI","n":94,"a":1597247788000,"p":146},{"i":"37i9dQZF1DWYxZc1Cgg8Ja","n":15,"a":1597097220000,"p":141},{"i":"37i9dQZEVXbJpRQ294oZ9N","n":27,"a":0,"p":125},{"i":"37i9dQZF1DWZuieNT0Gy18","n":56,"a":1596228667000,"p":124},{"i":"37i9dQZEVXbJWZV7aRNQck","n":22,"a":0,"p":122},{"i":"37i9dQZF1DX7kV7MLy24Ug","n":32,"a":1597260454000,"p":109},{"i":"37i9dQZF1DX0nc5UuGQPnQ","n":22,"a":1595948764000,"p":109},{"i":"37i9dQZEVXbM1qaaFAyPLz","n":15,"a":0,"p":100},{"i":"37i9dQZF1DXbDPWblNlzy4","n":15,"a":1597381380000,"p":90},{"i":"37i9dQZEVXbMTKZuy8ORFV","n":29,"a":0,"p":80},{"i":"37i9dQZF1DXctlngsnJR5k","n":23,"a":1596142458000,"p":79},{"i":"37i9dQZEVXbNF1heNYHDnE","n":24,"a":0,"p":77},{"i":"37i9dQZF1DX9235ICuUcIM","n":3,"a":1597099192000,"p":68},{"i":"37i9dQZF1DWTMcSlgDhjk8","n":48,"a":1597090662000,"p":56},{"i":"37i9dQZEVXbLo3yC8XJf1e","n":49,"a":0,"p":51},{"i":"37i9dQZF1DX2634ugjuuln","n":18,"a":1593710802000,"p":41},{"i":"37i9dQZF1DXaIfbw6rIKpz","n":10,"a":1593710940000,"p":34}],"pp":26550},"58":{"i":"0QtpKLa62AfLe5m0L2x3Gr","is":"USSD12000158","n":"No Vuelvas a Mí","a":[{"i":"6tkyhGe9hGI3Lcfo4gVh6Z","n":"ChocQuibTown"},{"i":"1pgDilWYDWLoOgGjf1iHNu","n":"Zion"}],"p":52,"r":"2020-06-12","l":"Sony Music Latin","im":"https://i.scdn.co/image/ab67616d0000b2738c863b2d14abdd5c3019625d","ps":[{"i":"37i9dQZF1DX9gKTxAbfFfX","n":53,"a":1596794849000,"p":436},{"i":"37i9dQZF1DWTD6JPQU0gqz","n":5,"a":1594927121000,"p":196}],"pp":632},"59":{"i":"5WGHknjgYatHVCFRTFB8QP","is":"USSD12000159","n":"Vuelve","a":[{"i":"6tkyhGe9hGI3Lcfo4gVh6Z","n":"ChocQuibTown"}],"p":58,"r":"2020-06-12","l":"Sony Music Latin","im":"https://i.scdn.co/image/ab67616d0000b2738c863b2d14abdd5c3019625d","ps":[{"i":"37i9dQZF1DX4TNDxNzIjRm","n":13,"a":1596465261000,"p":1073},{"i":"37i9dQZF1DX1QnNyJOBQBv","n":33,"a":1596775304000,"p":953},{"i":"37i9dQZF1DX5UTavgI6ivn","n":1,"a":1597113081000,"p":606},{"i":"1vIZxBcvgGHE9HXbQnzXYI","n":35,"a":1596723038000,"p":548},{"i":"37i9dQZF1DX57NRq0pf7ea","n":55,"a":1597096980000,"p":138},{"i":"37i9dQZF1DX36aMMENsgJy","n":27,"a":1594960980000,"p":90},{"i":"37i9dQZF1DWUArRC04H8rI","n":55,"a":1597204996000,"p":78},{"i":"37i9dQZF1DXaIfbw6rIKpz","n":45,"a":1593710940000,"p":24}],"pp":3510},"63":{"i":"4ZzJYm533TMFG7srgVldO1","is":"USSD12000163","n":"Quisiera","a":[{"i":"6tkyhGe9hGI3Lcfo4gVh6Z","n":"ChocQuibTown"},{"i":"0tmwSHipWxN12fsoLcFU3B","n":"Manuel Turizo"}],"p":53,"r":"2020-06-12","l":"Sony Music Latin","im":"https://i.scdn.co/image/ab67616d0000b2738c863b2d14abdd5c3019625d","ps":[{"i":"1p0OF8PV5BOMvhwO8J3zCM","n":30,"a":1596810422000,"p":122}],"pp":122},"64":{"i":"0LzO18oxrn394t6FqjrZsO","is":"USSD12000164","n":"No Hay Nadie Más","a":[{"i":"6tkyhGe9hGI3Lcfo4gVh6Z","n":"ChocQuibTown"},{"i":"1mcTU81TzQhprhouKaTkpq","n":"Rauw Alejandro"},{"i":"1Ts9of7VPZElwPQnqnDSfW","n":"Lyanno"}],"p":47,"r":"2020-06-12","l":"Sony Music Latin","im":"https://i.scdn.co/image/ab67616d0000b2738c863b2d14abdd5c3019625d","ps":[{"i":"37i9dQZF1DWYxZc1Cgg8Ja","n":53,"a":1597097220000,"p":96}],"pp":96},"65":{"i":"7kxrjibF93wyoPYnalR2xm","is":"USSD12000165","n":"Mala Mía","a":[{"i":"5Cg1uhz6CxzXKvguhnoFAp","n":"Lo Blanquito"}],"p":45,"r":"2020-07-24","l":"Sony Music Latin","im":"https://i.scdn.co/image/ab67616d0000b2730cc0a54338307afe0c213dfc","ps":[{"i":"37i9dQZF1DWXm5oABK4IDC","n":23,"a":1596202028000,"p":70}],"pp":70},"68":{"i":"7vpXKawR8GEUAz6FYPhbbO","is":"USSD12000168","n":"DALE CINTURA (Kuliki) (feat. Steve Aoki, Kiko El Crazy & Toño Rosario)","a":[{"i":"1TtXnWcUs0FCkaZDPGYHdf","n":"Darell"},{"i":"7cYik4OyfBXYV5Z2TI7p90","n":"Farina"},{"i":"7MP4jhYmFEgb0AtiOkw55s","n":"Play-N-Skillz"},{"i":"77AiFEVeAVj2ORpC85QVJs","n":"Steve Aoki"},{"i":"3NpG6SsHaQETkdQVZH6V1E","n":"Kiko el Crazy"},{"i":"4DjY0CaKAejJgghVHTaOUy","n":"Toño Rosario"}],"p":61,"r":"2020-06-01","l":"Sony Music Latin","im":"https://i.scdn.co/image/ab67616d0000b27386ea843956fc76101d68cb13","ps":[{"i":"37i9dQZF1DX7cmFV9rWM0u","n":7,"a":1596770872000,"p":1237},{"i":"37i9dQZF1DWWTS5vSPG86u","n":0,"a":1594344222000,"p":114}],"pp":1351},"72":{"i":"3KL1PYodWTfgeJ6ggHe4uD","is":"USSD12000172","n":"Entendido!","a":[{"i":"5GDuUaYx3PW3Wa64KxAAAO","n":"Lao Ra"}],"p":37,"r":"2020-06-19","l":"Sony Music Latin","im":"https://i.scdn.co/image/ab67616d0000b2733729f41a4768b246dfb15f89","ps":[{"i":"37i9dQZF1DWSWHOzidsSnO","n":2,"a":1596776520000,"p":139},{"i":"37i9dQZF1DWUArRC04H8rI","n":31,"a":1597204996000,"p":99},{"i":"37i9dQZF1DX6tPTxr8qwRe","n":36,"a":1597162018000,"p":14}],"pp":252},"75":{"i":"15OjBeqNX3bShsGYQbteRv","is":"USSD12000175","n":"La Tóxica","a":[{"i":"329e4yvIujISKGKz1BZZbO","n":"Farruko"}],"p":76,"r":"2020-07-24","l":"Sony Music Latin","im":"https://i.scdn.co/image/ab67616d0000b27300dbb42f00340f35ce0ec816","ps":[{"i":"37i9dQZF1DWY7IeIP1cdjF","n":19,"a":1597377660000,"p":2628},{"i":"37i9dQZF1DX10zKzsJ2jva","n":23,"a":1597377660000,"p":2583},{"i":"37i9dQZF1DWZoF06RIo9el","n":9,"a":1596811919000,"p":1085},{"i":"37i9dQZF1DX4oUPBOaEkL6","n":35,"a":1596653218000,"p":919},{"i":"37i9dQZF1DX5y71ufjoyXC","n":13,"a":1597377660000,"p":813},{"i":"37i9dQZF1DXclgCwbk0uat","n":43,"a":1597259989000,"p":776},{"i":"1vIZxBcvgGHE9HXbQnzXYI","n":11,"a":1596723038000,"p":697},{"i":"37i9dQZF1DX9gKTxAbfFfX","n":18,"a":1596794849000,"p":620},{"i":"37i9dQZF1DWUlCmB8llCTB","n":10,"a":1597377660000,"p":543},{"i":"37i9dQZEVXbL0GavIqMTeb","n":36,"a":0,"p":420},{"i":"37i9dQZF1DX6sLKL3qdVO1","n":36,"a":1597157997000,"p":317},{"i":"37i9dQZF1DXc9orRugI29r","n":47,"a":1597199632000,"p":232},{"i":"53gsoDSMuaYKyEBa2izvOV","n":33,"a":1596774383000,"p":185},{"i":"37i9dQZF1DX8XuzoFe1VZC","n":31,"a":1597080123000,"p":182},{"i":"37i9dQZF1DX57NRq0pf7ea","n":31,"a":1597096980000,"p":175},{"i":"37i9dQZF1DWUvCktKHpf5G","n":48,"a":1597263703000,"p":116},{"i":"37i9dQZF1DX4Ma23gvJILl","n":2,"a":1596161282000,"p":93},{"i":"37i9dQZF1DWXm5oABK4IDC","n":18,"a":1596202028000,"p":74},{"i":"37i9dQZF1DX1wIwohTkddk","n":8,"a":1597231542000,"p":65}],"pp":12523},"79":{"i":"4DXkg0aahmbBuTdINKZugg","is":"USSD12000179","n":"Hoy","a":[{"i":"5GcWBUX00IPuWVGMIRK1sS","n":"Residente"}],"p":64,"r":"2020-07-02","l":"Sony Music Latin","im":"https://i.scdn.co/image/ab67616d0000b273fbd2e734b9556732edeb7f18","ps":[{"i":"37i9dQZF1DX76Wlfdnj7AP","n":2,"a":1596660996000,"p":2667},{"i":"37i9dQZF1DX3rgIhQ2x809","n":9,"a":1596468477000,"p":217},{"i":"53gsoDSMuaYKyEBa2izvOV","n":27,"a":1596774383000,"p":196},{"i":"37i9dQZF1DX8XuzoFe1VZC","n":66,"a":1597080123000,"p":128},{"i":"37i9dQZF1DX0SZWVrotKn1","n":6,"a":1594357380000,"p":118},{"i":"37i9dQZF1DWXm5oABK4IDC","n":60,"a":1596202028000,"p":48}],"pp":3374},"84":{"i":"3DJkOQEj4u5vbPEavvbPT0","is":"USSD12000184","n":"La Sábana y los Pies","a":[{"i":"4QVBYiagIaa6ZGSPMbybpy","n":"Pedro Capó"}],"p":63,"r":"2020-07-23","l":"Sony Music Latin","im":"https://i.scdn.co/image/ab67616d0000b27355a8dd5d77b67f136777bbd7","ps":[{"i":"37i9dQZF1DX1QnNyJOBQBv","n":15,"a":1596775304000,"p":1142},{"i":"37i9dQZF1DX4TNDxNzIjRm","n":11,"a":1596465261000,"p":1094},{"i":"37i9dQZF1DWZoF06RIo9el","n":34,"a":1596811919000,"p":844},{"i":"1vIZxBcvgGHE9HXbQnzXYI","n":16,"a":1596723038000,"p":663},{"i":"37i9dQZF1DWTPDzakLfYZr","n":27,"a":1597092812000,"p":508},{"i":"37i9dQZF1DX8womvTyUjrN","n":25,"a":1596775658000,"p":376},{"i":"37i9dQZF1DXc9orRugI29r","n":46,"a":1597199632000,"p":235},{"i":"53gsoDSMuaYKyEBa2izvOV","n":23,"a":1596774383000,"p":204},{"i":"37i9dQZF1DX57NRq0pf7ea","n":26,"a":1597096980000,"p":184},{"i":"37i9dQZF1DX8XuzoFe1VZC","n":37,"a":1597080123000,"p":171},{"i":"37i9dQZF1DX4Ma23gvJILl","n":3,"a":1596161282000,"p":92},{"i":"37i9dQZF1DXbDPWblNlzy4","n":22,"a":1597381380000,"p":83},{"i":"37i9dQZF1DWXm5oABK4IDC","n":22,"a":1596202028000,"p":71}],"pp":5667},"87":{"i":"0zlnHTHiBQ68ZCAmTw5ozm","is":"USSD12000187","n":"Algo Mágico","a":[{"i":"1mcTU81TzQhprhouKaTkpq","n":"Rauw Alejandro"}],"p":74,"r":"2020-06-25","l":"Sony Music Latin","im":"https://i.scdn.co/image/ab67616d0000b2738d475e8cf8415d1c2587497f","ps":[{"i":"37i9dQZF1DXdnGF35OawbN","n":26,"a":1596466213000,"p":1519},{"i":"37i9dQZF1DWZoF06RIo9el","n":41,"a":1596811919000,"p":787},{"i":"37i9dQZF1DX5y71ufjoyXC","n":40,"a":1597377660000,"p":620},{"i":"1vIZxBcvgGHE9HXbQnzXYI","n":23,"a":1596723038000,"p":618},{"i":"37i9dQZF1DWSjuSq42neMu","n":29,"a":1597346520000,"p":395},{"i":"37i9dQZF1DX8DSRR3tGze6","n":15,"a":1596467081000,"p":236},{"i":"53gsoDSMuaYKyEBa2izvOV","n":20,"a":1596774383000,"p":210},{"i":"37i9dQZF1DX57NRq0pf7ea","n":54,"a":1597096980000,"p":139},{"i":"37i9dQZF1DWXDwGIM6EwQS","n":14,"a":1596462531000,"p":25}],"pp":4549},"88":{"i":"4ZRrLHqzhGRXYj2qcB4s5S","is":"USSD12000188","n":"Tattoo - Remix with Camilo","a":[{"i":"1mcTU81TzQhprhouKaTkpq","n":"Rauw Alejandro"},{"i":"28gNT5KBp7IjEOQoevXf9N","n":"Camilo"}],"p":91,"r":"2020-07-09","l":"Sony Music Latin","im":"https://i.scdn.co/image/ab67616d0000b273bbbcca8d3647640ce972d327","ps":[{"i":"37i9dQZF1DX10zKzsJ2jva","n":10,"a":1597377660000,"p":2944},{"i":"37i9dQZEVXbMDoHDwVN2tF","n":29,"a":0,"p":2938},{"i":"37i9dQZF1DXdnGF35OawbN","n":1,"a":1596466213000,"p":1953},{"i":"37i9dQZF1DX5BAPG29mHS8","n":13,"a":1597330282000,"p":1664},{"i":"37i9dQZF1DXaxEKcoCdWHD","n":0,"a":1597054769000,"p":1480},{"i":"37i9dQZF1DXbbu94YBG7Ye","n":1,"a":1597260236000,"p":1448},{"i":"37i9dQZF1DWSX4baQVDQut","n":4,"a":1595011744000,"p":1237},{"i":"37i9dQZF1DXclgCwbk0uat","n":1,"a":1597259989000,"p":1184},{"i":"37i9dQZF1DX4oUPBOaEkL6","n":10,"a":1596653218000,"p":1181},{"i":"37i9dQZEVXbNFJfN1Vw8d9","n":2,"a":0,"p":1081},{"i":"37i9dQZF1DX9Dh2wgiAwVX","n":11,"a":1595254335000,"p":1062},{"i":"37i9dQZF1DXcRXFNfZr7Tp","n":22,"a":1597377711000,"p":1039},{"i":"37i9dQZEVXbO3qyFxbkOE1","n":6,"a":0,"p":1031},{"i":"37i9dQZF1DWVskFRGurTfg","n":0,"a":1597155472000,"p":1027},{"i":"37i9dQZF1DX4TNDxNzIjRm","n":20,"a":1596465261000,"p":1000},{"i":"37i9dQZEVXbMMy2roB9myp","n":2,"a":0,"p":883},{"i":"37i9dQZEVXbLiRSasKsNU9","n":38,"a":0,"p":878},{"i":"37i9dQZF1DX3sCT1ItXgNd","n":2,"a":1596561624000,"p":866},{"i":"37i9dQZF1DX5y71ufjoyXC","n":9,"a":1597377660000,"p":847},{"i":"37i9dQZF1DX9vJ2U3sN7xj","n":16,"a":1596466363000,"p":807},{"i":"1vIZxBcvgGHE9HXbQnzXYI","n":1,"a":1596723038000,"p":771},{"i":"37i9dQZEVXbOa2lmxNORXQ","n":1,"a":0,"p":767},{"i":"37i9dQZF1DX9gKTxAbfFfX","n":0,"a":1596794849000,"p":742},{"i":"37i9dQZF1DXbvPjXfc8G9S","n":2,"a":1596668677000,"p":736},{"i":"37i9dQZF1DWU13kKnk03AP","n":60,"a":1596772860000,"p":706},{"i":"37i9dQZF1DX9KJJbsGEwfj","n":32,"a":1597291433000,"p":696},{"i":"37i9dQZF1DX9C8KzGEUKV4","n":0,"a":1597265062000,"p":633},{"i":"37i9dQZF1DWTPDzakLfYZr","n":7,"a":1597092812000,"p":621},{"i":"37i9dQZEVXbJfdy5b0KP7W","n":1,"a":0,"p":607},{"i":"37i9dQZEVXbL0GavIqMTeb","n":3,"a":0,"p":585},{"i":"37i9dQZF1DX1gRalH1mWrP","n":61,"a":1597347669000,"p":534},{"i":"37i9dQZF1DWVOLXBOylBUZ","n":10,"a":1597356952000,"p":478},{"i":"37i9dQZF1DWSpF87bP6JSF","n":0,"a":1596835915000,"p":436},{"i":"37i9dQZEVXbLuUZrygauiA","n":4,"a":0,"p":436},{"i":"37i9dQZF1DWSfv493aPhol","n":16,"a":1597182413000,"p":432},{"i":"37i9dQZF1DX4OjfOteYnH8","n":50,"a":1597118460000,"p":405},{"i":"37i9dQZF1DXbT1642xPu6H","n":7,"a":1597346498000,"p":393},{"i":"37i9dQZEVXbMfVLvbaC3bj","n":4,"a":0,"p":386},{"i":"00y6gxF3WUiOEnG9RPUe6l","n":3,"a":1596769502000,"p":379},{"i":"37i9dQZF1DWYNSDUeK85ev","n":20,"a":1597324764000,"p":362},{"i":"37i9dQZF1DXctZGldNPWLR","n":2,"a":1597251952000,"p":356},{"i":"37i9dQZEVXbNOUPGj7tW6T","n":6,"a":0,"p":356},{"i":"37i9dQZEVXbJlM6nvL1nD1","n":4,"a":0,"p":350},{"i":"37i9dQZEVXbJajpaXyaKll","n":3,"a":0,"p":344},{"i":"37i9dQZEVXbKAbrMR8uuf7","n":1,"a":0,"p":341},{"i":"37i9dQZEVXbMZAjGMynsQX","n":3,"a":0,"p":323},{"i":"37i9dQZEVXbN7gfhgaomhA","n":2,"a":0,"p":274},{"i":"37i9dQZF1DWUI9wBgUr4BH","n":50,"a":1597369448000,"p":273},{"i":"37i9dQZEVXbMJJi3wgRbAy","n":3,"a":0,"p":269},{"i":"37i9dQZEVXbKypXHVwk1f0","n":3,"a":0,"p":266},{"i":"37i9dQZF1DX8DSRR3tGze6","n":4,"a":1596467081000,"p":263},{"i":"37i9dQZEVXbKrooeK9WSFF","n":3,"a":0,"p":260},{"i":"53gsoDSMuaYKyEBa2izvOV","n":4,"a":1596774383000,"p":247},{"i":"37i9dQZEVXbJs8e2vk15a8","n":7,"a":0,"p":245},{"i":"37i9dQZEVXbJqfMFK4d691","n":4,"a":0,"p":241},{"i":"37i9dQZEVXbLy5tBFyQvd4","n":3,"a":0,"p":232},{"i":"37i9dQZF1DX57NRq0pf7ea","n":6,"a":1597096980000,"p":225},{"i":"37i9dQZF1DXdOe3IHMQPm8","n":17,"a":1597325283000,"p":205},{"i":"37i9dQZEVXbJp9wcIM9Eo5","n":4,"a":0,"p":202},{"i":"37i9dQZF1DX1KN7YrOIxQD","n":0,"a":1597354090000,"p":191},{"i":"37i9dQZEVXbLxoIml4MYkT","n":5,"a":0,"p":189},{"i":"37i9dQZEVXbJpRQ294oZ9N","n":2,"a":0,"p":160},{"i":"37i9dQZEVXbJWZV7aRNQck","n":0,"a":0,"p":152},{"i":"37i9dQZF1DWYxZc1Cgg8Ja","n":9,"a":1597097220000,"p":149},{"i":"37i9dQZF1DX7kV7MLy24Ug","n":1,"a":1597260454000,"p":149},{"i":"37i9dQZF1DX8XuzoFe1VZC","n":51,"a":1597080123000,"p":149},{"i":"37i9dQZEVXbIPOivNiyjjS","n":44,"a":0,"p":146},{"i":"37i9dQZEVXbNxY4E5g33Gy","n":6,"a":0,"p":140},{"i":"37i9dQZF1DX0nc5UuGQPnQ","n":0,"a":1595948764000,"p":135},{"i":"37i9dQZEVXbMIO7B1pcKUy","n":3,"a":0,"p":124},{"i":"37i9dQZEVXbKOefHPXPMyf","n":6,"a":0,"p":123},{"i":"37i9dQZF1DWZuieNT0Gy18","n":63,"a":1596228667000,"p":115},{"i":"37i9dQZEVXbM1qaaFAyPLz","n":2,"a":0,"p":114},{"i":"37i9dQZEVXbMTKZuy8ORFV","n":1,"a":0,"p":106},{"i":"37i9dQZF1DXctlngsnJR5k","n":2,"a":1596142458000,"p":97},{"i":"37i9dQZEVXbNF1heNYHDnE","n":2,"a":0,"p":96},{"i":"37i9dQZEVXbISk8kxnzfCq","n":2,"a":0,"p":95},{"i":"37i9dQZF1DWTMcSlgDhjk8","n":1,"a":1597090662000,"p":90},{"i":"37i9dQZEVXbLo3yC8XJf1e","n":2,"a":0,"p":82},{"i":"37i9dQZEVXbNpKdqfZ9Upp","n":6,"a":0,"p":82},{"i":"37i9dQZF1DX4Ma23gvJILl","n":22,"a":1596161282000,"p":76},{"i":"37i9dQZEVXbKgCVIE0PTOD","n":3,"a":0,"p":69},{"i":"37i9dQZF1DWXm5oABK4IDC","n":48,"a":1596202028000,"p":55},{"i":"37i9dQZF1DX4D8VqBKbhZX","n":50,"a":1597246976000,"p":24},{"i":"1jGO6qqS0NrzgTv465iaoO","n":14,"a":1595049880000,"p":12},{"i":"3qioe7W5u9MzslKPHK4FJQ","n":256,"a":1595563912000,"p":1}],"pp":45848},"89":{"i":"5Lg7nUobqmANgJAnb8XHWo","is":"USSD12000189","n":"Te Extraño :(","a":[{"i":"5KQX0Ui06LVm6PApyicRFK","n":"Rombai"}],"p":59,"r":"2020-07-09","l":"Sony Music Latin","im":"https://i.scdn.co/image/ab67616d0000b273713063a43214f3eaeb96a4ca","ps":[{"i":"37i9dQZF1DX8DBcbHcgPJw","n":8,"a":1597330493000,"p":926},{"i":"37i9dQZF1DWYNSDUeK85ev","n":45,"a":1597324764000,"p":281},{"i":"53gsoDSMuaYKyEBa2izvOV","n":17,"a":1596774383000,"p":217},{"i":"37i9dQZF1DX9o4SIlW5lWs","n":1,"a":1597330558000,"p":201},{"i":"37i9dQZF1DX8XuzoFe1VZC","n":57,"a":1597080123000,"p":140},{"i":"37i9dQZF1DX4Ma23gvJILl","n":46,"a":1596161282000,"p":60}],"pp":1825},"90":{"i":"4uoR6qeWeuL4Qeu2qJzkuG","is":"USSD12000190","n":"Hawái","a":[{"i":"1r4hJ1h58CWwUQe3MxPuau","n":"Maluma"}],"p":85,"r":"2020-07-29","l":"Sony Music Latin","im":"https://i.scdn.co/image/ab67616d0000b2734805528033046475b63f0fd5","ps":[{"i":"37i9dQZF1DX10zKzsJ2jva","n":5,"a":1597377660000,"p":3095},{"i":"37i9dQZF1DWY7IeIP1cdjF","n":4,"a":1597377660000,"p":3055},{"i":"37i9dQZF1DX5BAPG29mHS8","n":2,"a":1597330282000,"p":1858},{"i":"37i9dQZF1DWZjqjZMudx9T","n":3,"a":1597079421000,"p":1458},{"i":"37i9dQZF1DX6aTaZa0K6VA","n":20,"a":1597374120000,"p":1417},{"i":"37i9dQZF1DX1QnNyJOBQBv","n":0,"a":1596775304000,"p":1328},{"i":"37i9dQZF1DX4oUPBOaEkL6","n":9,"a":1596653218000,"p":1193},{"i":"37i9dQZF1DWZoF06RIo9el","n":2,"a":1596811919000,"p":1165},{"i":"37i9dQZF1DXcRXFNfZr7Tp","n":18,"a":1597377711000,"p":1081},{"i":"37i9dQZEVXbO3qyFxbkOE1","n":5,"a":0,"p":1041},{"i":"37i9dQZF1DXaxEKcoCdWHD","n":43,"a":1597054769000,"p":960},{"i":"37i9dQZF1DXbbu94YBG7Ye","n":42,"a":1597260236000,"p":959},{"i":"37i9dQZF1DXclgCwbk0uat","n":25,"a":1597259989000,"p":930},{"i":"37i9dQZEVXbNFJfN1Vw8d9","n":22,"a":0,"p":884},{"i":"1vIZxBcvgGHE9HXbQnzXYI","n":0,"a":1596723038000,"p":779},{"i":"37i9dQZEVXbOa2lmxNORXQ","n":0,"a":0,"p":774},{"i":"37i9dQZEVXbMMy2roB9myp","n":19,"a":0,"p":745},{"i":"37i9dQZF1DWUa8ZRTfalHk","n":66,"a":1597377688000,"p":722},{"i":"37i9dQZF1DXbvPjXfc8G9S","n":7,"a":1596668677000,"p":700},{"i":"37i9dQZF1DWTPDzakLfYZr","n":2,"a":1597092812000,"p":653},{"i":"37i9dQZF1DX9gKTxAbfFfX","n":17,"a":1596794849000,"p":626},{"i":"37i9dQZF1DXb6wQUgoZzUc","n":14,"a":1597184178000,"p":612},{"i":"37i9dQZF1DX9L93gfg5cPa","n":1,"a":1597179270000,"p":598},{"i":"37i9dQZF1DX9C8KzGEUKV4","n":7,"a":1597265062000,"p":590},{"i":"37i9dQZF1DWUlCmB8llCTB","n":2,"a":1597377660000,"p":588},{"i":"37i9dQZF1DX4OjfOteYnH8","n":13,"a":1597118460000,"p":587},{"i":"37i9dQZEVXbJfdy5b0KP7W","n":6,"a":0,"p":577},{"i":"37i9dQZF1DX6sLKL3qdVO1","n":0,"a":1597157997000,"p":456},{"i":"37i9dQZEVXbL0GavIqMTeb","n":28,"a":0,"p":455},{"i":"37i9dQZF1DWVOLXBOylBUZ","n":20,"a":1597356952000,"p":433},{"i":"37i9dQZF1DWSpF87bP6JSF","n":1,"a":1596835915000,"p":431},{"i":"37i9dQZF1DWZdsS73T1ogG","n":44,"a":1597204860000,"p":428},{"i":"37i9dQZF1DXbT1642xPu6H","n":1,"a":1597346498000,"p":417},{"i":"37i9dQZF1DX4KeocBrdbJg","n":6,"a":1597362176000,"p":367},{"i":"37i9dQZEVXbJlM6nvL1nD1","n":2,"a":0,"p":358},{"i":"37i9dQZF1DX1wsT9lb6K5b","n":10,"a":1596810420000,"p":314},{"i":"37i9dQZEVXbNOUPGj7tW6T","n":25,"a":0,"p":294},{"i":"37i9dQZF1DXc9orRugI29r","n":26,"a":1597199632000,"p":287},{"i":"37i9dQZEVXbMZAjGMynsQX","n":18,"a":0,"p":278},{"i":"37i9dQZF1DXbpmT3HUTsZm","n":54,"a":1597068060000,"p":267},{"i":"37i9dQZEVXbKAbrMR8uuf7","n":29,"a":0,"p":258},{"i":"37i9dQZEVXbMJJi3wgRbAy","n":12,"a":0,"p":246},{"i":"53gsoDSMuaYKyEBa2izvOV","n":7,"a":1596774383000,"p":240},{"i":"37i9dQZEVXbJqfMFK4d691","n":5,"a":0,"p":239},{"i":"37i9dQZF1DXdOe3IHMQPm8","n":5,"a":1597325283000,"p":231},{"i":"37i9dQZEVXbKypXHVwk1f0","n":19,"a":0,"p":226},{"i":"37i9dQZF1DX57NRq0pf7ea","n":9,"a":1597096980000,"p":219},{"i":"37i9dQZEVXbLy5tBFyQvd4","n":11,"a":0,"p":214},{"i":"37i9dQZF1DX6JcLkkShqRw","n":48,"a":1597374060000,"p":200},{"i":"37i9dQZF1DWZuieNT0Gy18","n":11,"a":1596228667000,"p":195},{"i":"37i9dQZF1DX8XuzoFe1VZC","n":27,"a":1597080123000,"p":190},{"i":"37i9dQZF1DWTJNl0K16Gxt","n":73,"a":1597356060000,"p":184},{"i":"37i9dQZF1DWTh5RC6ek3nb","n":74,"a":1597356060000,"p":181},{"i":"37i9dQZF1DX0MD19TXm0aV","n":43,"a":1597230824000,"p":179},{"i":"37i9dQZEVXbLxoIml4MYkT","n":12,"a":0,"p":177},{"i":"37i9dQZEVXbJp9wcIM9Eo5","n":20,"a":0,"p":172},{"i":"37i9dQZF1DWYxZc1Cgg8Ja","n":3,"a":1597097220000,"p":159},{"i":"37i9dQZF1DWUvCktKHpf5G","n":18,"a":1597263703000,"p":157},{"i":"37i9dQZF1DX7kV7MLy24Ug","n":13,"a":1597260454000,"p":132},{"i":"37i9dQZF1DXdWFnhAwkRZH","n":37,"a":1597330860000,"p":117},{"i":"37i9dQZF1DWSUbEozh68df","n":68,"a":1597330860000,"p":99},{"i":"37i9dQZF1DWXm5oABK4IDC","n":0,"a":1596202028000,"p":89},{"i":"37i9dQZF1DX6K3mlB5G3WG","n":13,"a":1596554738000,"p":88},{"i":"37i9dQZF1DX1wIwohTkddk","n":3,"a":1597231542000,"p":68},{"i":"7H3cvnmGq6Ut1brPKbFpDq","n":56,"a":1597043781000,"p":30},{"i":"3qioe7W5u9MzslKPHK4FJQ","n":95,"a":1596250235000,"p":7}],"pp":38057},"92":{"i":"69pyUc13LhpXAyXtcyutk9","is":"USSD12000192","n":"Carne - Merengue Electrónico Remix","a":[{"i":"5RzT7CM6Ot0sh0EHefMicV","n":"Maffio"},{"i":"4DjY0CaKAejJgghVHTaOUy","n":"Toño Rosario"},{"i":"1noWnd8QFQD9VLxWEeo4Zf","n":"Don Miguelo"}],"p":46,"r":"2020-07-10","l":"Sony Music Latin","im":"https://i.scdn.co/image/ab67616d0000b273d4aca41b7c04a7be7022a754","ps":[{"i":"37i9dQZF1DWZVuIRLEh0tE","n":1,"a":1594344126000,"p":198},{"i":"37i9dQZF1DWYr67eGue7WT","n":0,"a":1594344110000,"p":138},{"i":"37i9dQZF1DWWTS5vSPG86u","n":4,"a":1594344222000,"p":109}],"pp":445},"93":{"i":"71oz9Wgbrm873aMlVBrDKR","is":"USSD12000193","n":"Desahogo (feat. Carla Morrison)","a":[{"i":"1SupJlEpv7RS2tPNRaHViT","n":"Nicky Jam"},{"i":"0XK6kT7xcZAlcYrNjOgzJe","n":"Carla Morrison"}],"p":71,"r":"2020-06-28","l":"Sony Music Latin","im":"https://i.scdn.co/image/ab67616d0000b273a5fcd8a2f698769ef7b78c8d","ps":[{"i":"37i9dQZF1DWZoF06RIo9el","n":44,"a":1596811919000,"p":764},{"i":"37i9dQZF1DX5y71ufjoyXC","n":39,"a":1597377660000,"p":626},{"i":"37i9dQZF1DX40O80BIPklU","n":4,"a":1597381260000,"p":321},{"i":"37i9dQZF1DX8XuzoFe1VZC","n":41,"a":1597080123000,"p":165},{"i":"37i9dQZF1DWVeItqkdELaR","n":37,"a":1595937694000,"p":131},{"i":"37i9dQZF1DX5moeZr1JWKb","n":12,"a":1596173760000,"p":78},{"i":"37i9dQZF1DWSq30bHsgNR5","n":1,"a":1596477009000,"p":33}],"pp":2118},"96":{"i":"3VvA1wSxukMLsvXoXtlwWx","is":"USSD12000196","n":"Hecha Pa' Mi","a":[{"i":"2NfSBtmWe7oPw1EmetJVso","n":"Boza"}],"p":54,"r":"2020-07-31","l":"Sony Music Latin","im":"https://i.scdn.co/image/ab67616d0000b2735921096535733d90092393b6","ps":[{"i":"37i9dQZEVXbKypXHVwk1f0","n":2,"a":0,"p":269}],"pp":269},"97":{"i":"4n98DgeQFXDsz15Wi6uT70","is":"USSD12000197","n":"Hola","a":[{"i":"2NfSBtmWe7oPw1EmetJVso","n":"Boza"}],"p":48,"r":"2020-07-31","l":"Sony Music Latin","im":"https://i.scdn.co/image/ab67616d0000b2735921096535733d90092393b6","ps":[{"i":"37i9dQZEVXbKypXHVwk1f0","n":39,"a":0,"p":185}],"pp":185},"98":{"i":"55uacpWJsxnD9J2rgDs6Gm","is":"USSD12000198","n":"Bandida","a":[{"i":"2NfSBtmWe7oPw1EmetJVso","n":"Boza"}],"p":53,"r":"2020-07-31","l":"Sony Music Latin","im":"https://i.scdn.co/image/ab67616d0000b2735921096535733d90092393b6","ps":[{"i":"37i9dQZF1DWZoF06RIo9el","n":21,"a":1596811919000,"p":962},{"i":"37i9dQZF1DWZdsS73T1ogG","n":0,"a":1597204860000,"p":667},{"i":"37i9dQZF1DX4OjfOteYnH8","n":25,"a":1597118460000,"p":521},{"i":"37i9dQZEVXbKypXHVwk1f0","n":9,"a":0,"p":250},{"i":"37i9dQZF1DWWyiRTvabqLE","n":4,"a":1596168060000,"p":47}],"pp":2447}},"s":[]}