{"d":{"1842":{"i":"05vWQ6vbNSX1XyeQLwYloQ","is":"QZHZ42061842","n":"120 Barras: Capítulo 5","a":[{"i":"6tJRAxu0HwB2GI9GueEj4l","n":"Faruz Feet"}],"p":45,"r":"2020-07-03","l":"FARUZ FEET","im":"https://i.scdn.co/image/ab67616d0000b273ae1e3d9220be02012a5dfb3b","ps":[{"i":"37i9dQZF1DWVFZbCNivv6B","n":50,"a":1597381260000,"p":346},{"i":"37i9dQZF1DXc5PHJQUwAnG","n":19,"a":1597279562000,"p":298}],"pp":644},"1994":{"i":"2SlC69Ah60jqox6E5RjjjT","is":"QZHZ42061994","n":"Vivendo de Sinais - Live","a":[{"i":"74B3SJ1xNHK3VS4T9i2TvQ","n":"Banda Magníficos"}],"p":33,"r":"2020-06-12","l":"Banda Magníficos Oficial","im":"https://i.scdn.co/image/ab67616d0000b2736a1e439a052f2c2f1f80338a","ps":[{"i":"37i9dQZF1DWTo645rcXEVL","n":20,"a":1597374120000,"p":54}],"pp":54},"2449":{"i":"7LryHNIEa0AtcaGjr5744f","is":"QZHZ42062449","n":"Catucadão","a":[{"i":"0UkgR9OaNIythB9LMU6ND1","n":"Shevchenko e Elloco"},{"i":"4d175LvxCzxt5vHbJyv49q","n":"Mc Dricka"},{"i":"02RgHAzh0DVNQR24lBuGOI","n":"MC Marley"},{"i":"5P0GB7AHjAnR2Q2RWKWJab","n":"Biel XCamoso"}],"p":51,"r":"2020-07-10","l":"Tropa Produtora 81","im":"https://i.scdn.co/image/ab67616d0000b273ca9e4ed32e9250764c6b149e","ps":[{"i":"37i9dQZF1DWZgZxLup5qYy","n":7,"a":1597374120000,"p":556},{"i":"67HYZM7wyXrABqp60yEILo","n":19,"a":1596191729000,"p":14}],"pp":570},"2514":{"i":"7FfMRD9T0xCyYYk2DpUiy2","is":"QZHZ42062514","n":"Da Ideia","a":[{"i":"0UkgR9OaNIythB9LMU6ND1","n":"Shevchenko e Elloco"},{"i":"7GlAYFuTPHWxfieITHslOU","n":"MC 10G"},{"i":"4d175LvxCzxt5vHbJyv49q","n":"Mc Dricka"},{"i":"7GGbCZSuOMfQyCHRnclPyh","n":"Salah do Nordeste"}],"p":47,"r":"2020-07-03","l":"Tropa Produtora 81","im":"https://i.scdn.co/image/ab67616d0000b2739249243f5ea93bca3f8e076a","ps":[{"i":"37i9dQZF1DWZgZxLup5qYy","n":31,"a":1597374120000,"p":437}],"pp":437},"2980":{"i":"3EpXLvuT3XzEhAR6CAEGnn","is":"QZHZ42062980","n":"Needed Somebody","a":[{"i":"1WtJGNrnGxmw7osdorX4iM","n":"Willie Shaw"}],"p":48,"r":"2020-06-26","l":"Willie Shaw","im":"https://i.scdn.co/image/ab67616d0000b273c168a9c38a01ca163ae5b446","ps":[{"i":"37i9dQZF1DX3u9TSHqpdJC","n":83,"a":1593655010000,"p":128},{"i":"37i9dQZF1DWTvM9hRJYH10","n":67,"a":1597093583000,"p":58}],"pp":186},"3026":{"i":"1EwsK15DkAj6vzergHyapI","is":"QZHZ42063026","n":"María Sueños","a":[{"i":"0FC78OyyffAXNtDslf56mG","n":"Desire Mandrile"},{"i":"0ZwjmGhps2YvUMzB7ihFV8","n":"Adrian Bello"}],"p":23,"r":"2020-07-17","l":"Desire Mandrile","im":"https://i.scdn.co/image/ab67616d0000b273ed0a99b9f8f06c822428e4b6","ps":[{"i":"37i9dQZF1DXcWcRIYY41Ix","n":17,"a":1596756195000,"p":198}],"pp":198},"3475":{"i":"4ljgZAskHzgKGg6GcVIsGP","is":"QZHZ42063475","n":"Senta e Se Acaba","a":[{"i":"1vQmEkUObXvubDjIJb4Urv","n":"DJ Tezinho"},{"i":"4EMRE0wdcc2xjv1PCmTqUU","n":"MC Menor MT"},{"i":"3SYCuA9OEaTpIfZyIyC9nk","n":"MC 27"}],"p":28,"r":"2020-06-19","l":"Tezinho Records","im":"https://i.scdn.co/image/ab67616d0000b2738212950c907bd47b764d76fc","ps":[{"i":"37i9dQZF1DWW2VVq6VvPuS","n":76,"a":1597081346000,"p":100}],"pp":100},"3827":{"i":"6mystx9yyelLQbIcnsXu5X","is":"QZHZ42063827","n":"Madrugada Brinca","a":[{"i":"5s9djBRIl012hKNW3ybaOZ","n":"Jovem Creator"},{"i":"7julRQKxhcCvHDB7gr7alR","n":"Roddy"}],"p":21,"r":"2020-06-26","l":"102 Criações / Feel the Sound Energy","im":"https://i.scdn.co/image/ab67616d0000b273e82ad219c132c02ed5130fdc","ps":[{"i":"37i9dQZF1DX0H97kz3DdJ6","n":33,"a":1597166765000,"p":216}],"pp":216},"4227":{"i":"2TuyDSC85ybJDA7sM0Fz7T","is":"QZHZ42064227","n":"Macete 2","a":[{"i":"1iKxeI1ud2pXD4U9atJ4RS","n":"Mc Balakinha"},{"i":"28QnIZpWxKcxuSk4iRLUgX","n":"Mc Morena"}],"p":56,"r":"2020-06-05","l":"Tudo Nosso Oficial","im":"https://i.scdn.co/image/ab67616d0000b2735d93afb041f876a5c3ef3cf2","ps":[{"i":"37i9dQZF1DWZgZxLup5qYy","n":28,"a":1597374120000,"p":451},{"i":"44HCx45fac9vrwqne4Sw41","n":28,"a":1597409496000,"p":34},{"i":"5teJDcsrQJ9QZGYugoq2MB","n":55,"a":1596802899000,"p":33},{"i":"1hCQkNupVD4HqfTS4GnMwC","n":10,"a":1597409134000,"p":32},{"i":"0IhVk09lB03uNccMTUemfd","n":18,"a":1596802986000,"p":17},{"i":"5lEqTwrozbpYcTrPObzPIc","n":8,"a":1595590362000,"p":16},{"i":"67HYZM7wyXrABqp60yEILo","n":8,"a":1595590523000,"p":16},{"i":"5mjOjSvZizVAUNjasnSy02","n":8,"a":1596803001000,"p":15},{"i":"6dMJWeknEufFRxtTRB7Ufx","n":0,"a":1593770002000,"p":15},{"i":"3WH1Mj7Vu760FuV4nz8G4K","n":1,"a":1596191262000,"p":14},{"i":"52h85JuYPqr16CSqPETaxf","n":23,"a":1597409323000,"p":10},{"i":"7hCUXE2FcQttBUJVz811BS","n":55,"a":1597409476000,"p":8}],"pp":661},"4646":{"i":"4rPS6ychPbKxfnoefkGN60","is":"QZHZ42064646","n":"Na de Na - Remix","a":[{"i":"4ofHy9bcqR6gBvOBIvCyC0","n":"Fernanda"},{"i":"31VFEohvhOUKrtAONEBhMG","n":"Kenia OS"}],"p":51,"r":"2020-06-12","l":"Only Hits Music","im":"https://i.scdn.co/image/ab67616d0000b2737c71bf79e43409b9f32a51d8","ps":[{"i":"37i9dQZF1DX5hrSNdL1ktS","n":18,"a":1597194427000,"p":103}],"pp":103},"4976":{"i":"0eyRvKpFWHbGoSnFjeIelj","is":"QZHZ42064976","n":"Vai Joga Devagar","a":[{"i":"7ySZCEP4HFGckYYPK5rqFI","n":"Melody"},{"i":"45Hr5etuwmSx4gSyn5qSeW","n":"MC Dede"}],"p":45,"r":"2020-06-09","l":"Melody","im":"https://i.scdn.co/image/ab67616d0000b273ef374124cbfef81ad7eb82e4","ps":[{"i":"37i9dQZF1DWW6EwN6CPxGO","n":13,"a":1597081521000,"p":560}],"pp":560},"6005":{"i":"2MTqvrqMO0RxTpO20yPsff","is":"QZHZ42066005","n":"Mar de Sábanas","a":[{"i":"3dPV32rIkpT2Y7w8mwkg2l","n":"Jaime Kohen"}],"p":37,"r":"2020-07-09","l":"ASHA GROW","im":"https://i.scdn.co/image/ab67616d0000b2738684683219ab4536eac048b1","ps":[{"i":"37i9dQZF1DX6LVkNunXMAU","n":38,"a":1597074766000,"p":120}],"pp":120},"6711":{"i":"2pyls3bhWqxrQ3I71cRngO","is":"QZHZ42066711","n":"Into Me","a":[{"i":"1a3wNO8RPhwmEBZqm68aqU","n":"Chi Ching Ching"}],"p":34,"r":"2020-06-19","l":"Money Matters Entertainment","im":"https://i.scdn.co/image/ab67616d0000b2738d1db263fe40af552f1d019d","ps":[{"i":"37i9dQZF1DXan38dNVDdl4","n":24,"a":1597073242000,"p":746},{"i":"37i9dQZF1DX7g6vTI60Om0","n":25,"a":1597060188000,"p":132}],"pp":878},"6713":{"i":"6rQUBkFheZaxxE3l4kiazb","is":"QZHZ42066713","n":"Ya Ya Ya Ya Ya Ya","a":[{"i":"6iGnMrpoPy3fPn2JwawcUI","n":"Future Fambo"}],"p":34,"r":"2020-06-19","l":"Money Matters Entertainment","im":"https://i.scdn.co/image/ab67616d0000b2730cbc57ec62573cbc01ca2bb8","ps":[{"i":"37i9dQZF1DXan38dNVDdl4","n":18,"a":1597073242000,"p":793}],"pp":793},"7000":{"i":"2jiwqVNF9zYfPdyOrez8hJ","is":"QZHZ42067000","n":"Hoy Me Tengo Que Ir","a":[{"i":"63AURDJ3zaxKaBcrm9q74B","n":"Emilio"}],"p":47,"r":"2020-06-26","l":"Boomerang Latin Music","im":"https://i.scdn.co/image/ab67616d0000b27397db0a6773152919afd7e49e","ps":[{"i":"37i9dQZF1DX6LVkNunXMAU","n":47,"a":1597074766000,"p":110}],"pp":110},"7413":{"i":"1lZaf727kwMtrRYlug9ceZ","is":"QZHZ42067413","n":"Eu Te Louvo","a":[{"i":"3PXIlnaU0gOLh7x0jIXvnt","n":"Miriam dos Passos"}],"p":29,"r":"2020-06-06","l":"Miriam dos Passos","im":"https://i.scdn.co/image/ab67616d0000b2738e998a4adba0986ecc416e05","ps":[{"i":"37i9dQZF1DWTvrPFPIwgwG","n":18,"a":1597374120000,"p":150}],"pp":150},"7542":{"i":"1HcAS10EG5WCxc52KwkIOi","is":"QZHZ42067542","n":"Control","a":[{"i":"0Cgas3vfskrETY9NgmrwHk","n":"COLOR"}],"p":28,"r":"2020-07-03","l":"COLOR","im":"https://i.scdn.co/image/ab67616d0000b2739e31e90db2b20575053e6080","ps":[{"i":"37i9dQZF1DX07RJCJCOYpi","n":7,"a":1594666859000,"p":1248}],"pp":1248},"7844":{"i":"4ZtCVLrKsOqgLnAH5LDwSR","is":"QZHZ42067844","n":"La Fuga","a":[{"i":"3KaNWDYObY73SDpcZBRzuw","n":"Irepelusa"}],"p":44,"r":"2020-07-03","l":"Irepelusa","im":"https://i.scdn.co/image/ab67616d0000b273bc4196ae365c1a2a415c2d48","ps":[{"i":"37i9dQZF1DXcjpPPxCzYRE","n":34,"a":1595968446000,"p":324},{"i":"37i9dQZF1DX56TFraF4fNu","n":7,"a":1597383480000,"p":136},{"i":"37i9dQZF1DWYxZc1Cgg8Ja","n":40,"a":1597381320000,"p":109}],"pp":569},"7865":{"i":"0c3XOZqhx4xO6BWJAA1gjU","is":"QZHZ42067865","n":"Does She Know","a":[{"i":"4vqV8IpWyagD7V8RjMO63g","n":"17 Memphis"}],"p":41,"r":"2020-06-26","l":"17 Memphis","im":"https://i.scdn.co/image/ab67616d0000b273cac7b51c6f89808cf40f5329","ps":[{"i":"37i9dQZF1DX5mB2C8gBeUM","n":41,"a":1596254460000,"p":588},{"i":"37i9dQZF1DWTvM9hRJYH10","n":16,"a":1597093583000,"p":97}],"pp":685},"7878":{"i":"2MpdpMXkmi0vvjORN0yrDM","is":"QZHZ42067878","n":"Estás Ahí","a":[{"i":"5HkbqKHZAvQjhjkhYm6mp2","n":"Pavlo"}],"p":36,"r":"2020-07-17","l":"PAVLO","im":"https://i.scdn.co/image/ab67616d0000b273fa8bd4ca7e551299dbc265f3","ps":[{"i":"37i9dQZF1DX2R0a3scWaq6","n":42,"a":1597080452000,"p":111}],"pp":111},"8177":{"i":"2lJdtJfH6mB80CWTw9xzcN","is":"QZHZ42068177","n":"La Canalla","a":[{"i":"5RN0qzNnwv5WsXSNiDjuio","n":"El Super Show De Los Vaskez"}],"p":0,"r":"2020-08-14","l":"Saps Records","im":"https://i.scdn.co/image/ab67616d0000b273775fe4edb9e0e9c2e2a473e0","ps":[{"i":"37i9dQZF1DXatk5BgNhCd7","n":15,"a":1597381320000,"p":43}],"pp":43},"8973":{"i":"6cTSInCxBcwkxzPkPWgeZa","is":"QZHZ42068973","n":"Olé","a":[{"i":"3TqicTPfXQLiPPZWKtHk0m","n":"Tayko"},{"i":"3KaNWDYObY73SDpcZBRzuw","n":"Irepelusa"},{"i":"5KhJh3jJOH5EkZiplQLw5h","n":"Veztalone"},{"i":"6ybUCb9uQ4fd6gtIptuaYO","n":"Comida Para Llevar"}],"p":40,"r":"2020-06-13","l":"Comida para llevar","im":"https://i.scdn.co/image/ab67616d0000b27303de03d80a32a08a74d07816","ps":[{"i":"37i9dQZF1DWTtgIvO0zxTI","n":45,"a":1597381320000,"p":129}],"pp":129},"9840":{"i":"5xoWCaXcNKj5S5goiVLBFc","is":"QZHZ42069840","n":"Sin Miedo a Ser","a":[{"i":"5bTN0MgAA8rwwi16VuwXwA","n":"Ciudad Nómade"}],"p":24,"r":"2020-07-17","l":"Ciudad Nómade","im":"https://i.scdn.co/image/ab67616d0000b2733d975db97d96dd68461b015b","ps":[{"i":"37i9dQZF1DX3TKWnpd3vOb","n":5,"a":1596772860000,"p":397},{"i":"37i9dQZF1DX5EaeKkdbBg0","n":63,"a":1597174408000,"p":144}],"pp":541},"0615":{"i":"3czhw7W0PTAIROkL1tcsKX","is":"QZHZ42060615","n":"Artistas da Rua","a":[{"i":"6AVuBAosGPLRJYwoJ88wtt","n":"Derxan"}],"p":21,"r":"2020-06-08","l":"Derxan","im":"https://i.scdn.co/image/ab67616d0000b273fc1b47e020cddceaeafe0011","ps":[{"i":"37i9dQZF1DX0EaLv8xHmij","n":15,"a":1597374120000,"p":30}],"pp":30},"0355":{"i":"4Nz2Wbn4DMcRnaJD66JJZb","is":"QZHZ42060355","n":"Salsa Perucha","a":[{"i":"25gsQNkL2qTq778NWyughs","n":"Josimar y Su Yambú"}],"p":42,"r":"2020-07-03","l":"JJ Records","im":"https://i.scdn.co/image/ab67616d0000b27339555bd206b633c1ddd53581","ps":[{"i":"37i9dQZF1DX1UHxedJfnRM","n":16,"a":1596776580000,"p":171}],"pp":171},"0641":{"i":"1o5VCkPJnxheI2v2fYxx9o","is":"QZHZ42060641","n":"Mentira","a":[{"i":"2aYJnf8uGK6sH46VTa4xjX","n":"Sami Duque"}],"p":50,"r":"2020-06-19","l":"Sami Duque","im":"https://i.scdn.co/image/ab67616d0000b273560070b27c92f543442dfed8","ps":[{"i":"37i9dQZF1DWZMtkg0cMXbp","n":41,"a":1596146520000,"p":229}],"pp":229}},"s":[]}