{"d":{"14":{"i":"0E21gHcH91EvoQgQN97dOP","is":"THG012000014","n":"วรรณคดีสีชมพู","a":[{"i":"19Qamuu4Xq2ZWxvVt9KLpt","n":"Paowalee Pornpimon"},{"i":"4QLlbZcntdcWpm40NooC2M","n":"Maiyarap"}],"p":39,"r":"2020-01-23","l":"GMM Grammy PCL.","im":"https://i.scdn.co/image/ab67616d0000b273682b4cc485318926baf2ca84","ps":[{"i":"37i9dQZF1DWZxuB1jS26mS","n":4,"a":1594924735000,"p":69}],"pp":69},"17":{"i":"014049hGhOzw7on3aGWehD","is":"THG012000017","n":"สัญญาณอันตราย","a":[{"i":"03PmA3VuwfyZVA0rel561k","n":"Tai Orathai"}],"p":42,"r":"2020-01-24","l":"GMM Grammy PCL.","im":"https://i.scdn.co/image/ab67616d0000b2739445a12cff0325c87356b016","ps":[{"i":"37i9dQZF1DXasLXGV6xWIC","n":20,"a":1597380749000,"p":177},{"i":"37i9dQZF1DXaMYpIMHCml5","n":21,"a":1594751814000,"p":92}],"pp":269},"18":{"i":"1z6ZFJA675rNhVpHatkwTa","is":"THG012000018","n":"ยืนหนึ่ง","a":[{"i":"5ZRMbbbfVXx4ACoGjuF2wP","n":"ZURIC"}],"p":22,"r":"2020-01-22","l":"GMM Grammy PCL.","im":"https://i.scdn.co/image/ab67616d0000b273e1a3865dad6e8667bb4066f2","ps":[{"i":"37i9dQZF1DX9dXO59fQBta","n":46,"a":1595947370000,"p":53}],"pp":53},"31":{"i":"7eoYD5rJbvcmVusxPxPJq9","is":"THG012000031","n":"ไม่ไหวอย่าฝืน","a":[{"i":"2TSyWXSQwvQLPQJbR6ryZX","n":"Palaphol"}],"p":35,"r":"2020-02-07","l":"GMM Grammy PCL.","im":"https://i.scdn.co/image/ab67616d0000b273edb64c0441dc801d7b175f01","ps":[{"i":"37i9dQZF1DX4tHo2ftQyun","n":44,"a":1597159750000,"p":180}],"pp":180},"65":{"i":"50YCZygIBKbV5hBYeipuGc","is":"THG012000065","n":"คนอยู่ไกลไม่มีสิทธิ์","a":[{"i":"4bZj4Lzi37PZlNPhix6zvH","n":"SDF X ลำเพลิน วงศกร"}],"p":23,"r":"2020-02-12","l":"GMM Grammy PCL.","im":"https://i.scdn.co/image/ab67616d0000b273f8ce205e7fac8d105087165a","ps":[{"i":"37i9dQZF1DWZxuB1jS26mS","n":22,"a":1594924735000,"p":57}],"pp":57},"67":{"i":"3GbMONlqujFp7yAWf9fYm8","is":"THG012000067","n":"ยุติ-ธรรม - เพลงประกอบภาพยนตร์ คืนยุติธรรม","a":[{"i":"0CR1aLS3JQTlekHgHTga60","n":"TaitosmitH"}],"p":41,"r":"2020-07-24","l":"GMM Grammy PCL.","im":"https://i.scdn.co/image/ab67616d0000b273aa3d5e0aecef011a512b1f52","ps":[{"i":"37i9dQZF1DX9oDJRGBpCWZ","n":4,"a":1597345460000,"p":142}],"pp":142},"71":{"i":"5wQ5UOc71CBq8XnnfqaBBt","is":"THG012000071","n":"แค่คำเดียว - เพลงประกอบละคร หนี้เสน่หา","a":[{"i":"5YmEu8ngufjZCsX7UzW9YF","n":"Neung Apiwat"}],"p":10,"r":"2020-02-13","l":"GMM Grammy PCL.","im":"https://i.scdn.co/image/ab67616d0000b2731096993c7f6caad0e419f421","ps":[{"i":"37i9dQZF1DWTzbE633ojB8","n":25,"a":1594923414000,"p":66}],"pp":66},"72":{"i":"6IitkM7xiuKhDXzshXUnRa","is":"THG012000072","n":"เลือกคนที่เขารักเรา","a":[{"i":"1qAOsY7jv9GFTv4HoVof5P","n":"Three Man Down"}],"p":63,"r":"2020-02-15","l":"GMM Grammy PCL.","im":"https://i.scdn.co/image/ab67616d0000b273c3b8cd477408c407653a62ad","ps":[{"i":"37i9dQZF1DXdzw50tzi795","n":26,"a":1596988032000,"p":293},{"i":"37i9dQZF1DXc51TI5dx7RC","n":29,"a":1597254059000,"p":263},{"i":"37i9dQZEVXbMnz8KIWsvf9","n":26,"a":0,"p":219},{"i":"37i9dQZF1DWW1S2VXZ4bIj","n":24,"a":1597381741000,"p":211},{"i":"37i9dQZF1DX8peoGqrSg0H","n":23,"a":1596988279000,"p":187},{"i":"37i9dQZF1DX2wrHNWlb0Eu","n":35,"a":1597160087000,"p":136},{"i":"37i9dQZF1DWTlbUjNA5MKD","n":28,"a":1597161200000,"p":88},{"i":"37i9dQZF1DX4Pso0u1C9Qx","n":45,"a":1596646527000,"p":59},{"i":"37i9dQZF1DX9dXO59fQBta","n":39,"a":1595947370000,"p":57}],"pp":1513},"73":{"i":"3OmtwG4oNhW0ZhynMis6Js","is":"THG012000073","n":"จองศาลาให้อ้ายแน","a":[{"i":"0rFWIp8ROPB3hLhJUNCGQq","n":"ลำเพลิน วงศกร"}],"p":26,"r":"2020-02-19","l":"GMM Grammy PCL.","im":"https://i.scdn.co/image/ab67616d0000b2737574dce132f32aeca63e08db","ps":[{"i":"37i9dQZF1DXaMYpIMHCml5","n":15,"a":1594751814000,"p":97}],"pp":97},"74":{"i":"7FrmO0hRB7eiBbQwXm0kbv","is":"THG012000074","n":"จนวันสุดท้าย - เพลงประกอบละคร ไปให้ถึงดวงดาว","a":[{"i":"27OaUzPoSIktzF5MnYPEmX","n":"Boy Peacemaker"}],"p":31,"r":"2020-02-20","l":"GMM Grammy PCL.","im":"https://i.scdn.co/image/ab67616d0000b27333cedf27f4eab8af383809c3","ps":[{"i":"37i9dQZF1DX2wrHNWlb0Eu","n":21,"a":1597160087000,"p":156},{"i":"37i9dQZF1DWTzbE633ojB8","n":29,"a":1594923414000,"p":64}],"pp":220},"76":{"i":"0F7jE0agpramWwK5GtRCBh","is":"THG012000076","n":"พร้อม - Acoustic","a":[{"i":"3ubzA3oelaUG8pvmDqftyf","n":"SIN"}],"p":40,"r":"2020-02-20","l":"GMM Grammy PCL.","im":"https://i.scdn.co/image/ab67616d0000b27328813e1881c658ff4dd4b3d9","ps":[{"i":"37i9dQZF1DX0bGxKepv6YZ","n":19,"a":1594575186000,"p":214}],"pp":214},"77":{"i":"5WHldZsdqAeLx9heJ5cIQH","is":"THG012000077","n":"ติดกับ - เพลงประกอบซีรีส์ เพราะเราคู่กัน","a":[{"i":"5nkD00FEf53rM9s4v33uFx","n":"Max Jenmana"}],"p":57,"r":"2020-02-19","l":"GMM Grammy PCL.","im":"https://i.scdn.co/image/ab67616d0000b27328b1f51cf8875b97c3d33c1c","ps":[{"i":"37i9dQZF1DX76P8iPXU0uQ","n":15,"a":1595948951000,"p":100},{"i":"37i9dQZF1DWZRLdKC8qik7","n":27,"a":1597160900000,"p":93},{"i":"37i9dQZF1DX9dXO59fQBta","n":24,"a":1595947370000,"p":66},{"i":"37i9dQZF1DWTzbE633ojB8","n":27,"a":1594923414000,"p":65},{"i":"37i9dQZF1DX6Th1cQfdJop","n":31,"a":1595949440000,"p":61}],"pp":385},"79":{"i":"4Cg2XGrrrczeZRPOnlAG67","is":"THG012000079","n":"คิด(แต่ไม่)ถึง (Same Page?)","a":[{"i":"4esoPgrgPKbWa6gwU8EGmH","n":"Tilly Birds"}],"p":69,"r":"2020-02-26","l":"GMM Grammy PCL.","im":"https://i.scdn.co/image/ab67616d0000b273e4c3cc9230e81286c06babe1","ps":[{"i":"37i9dQZF1DXdzw50tzi795","n":1,"a":1596988032000,"p":377},{"i":"37i9dQZF1DXc51TI5dx7RC","n":1,"a":1597254059000,"p":348},{"i":"37i9dQZEVXbMnz8KIWsvf9","n":1,"a":0,"p":281},{"i":"37i9dQZF1DWW1S2VXZ4bIj","n":15,"a":1597381741000,"p":231},{"i":"37i9dQZF1DX8peoGqrSg0H","n":13,"a":1596988279000,"p":207},{"i":"37i9dQZF1DX4tHo2ftQyun","n":37,"a":1597159750000,"p":193},{"i":"37i9dQZF1DWXPoAK0p4FcE","n":28,"a":1597396939000,"p":148},{"i":"37i9dQZF1DWUeFzTSNBzKM","n":48,"a":1597342840000,"p":117},{"i":"37i9dQZF1DX7wnCfGfUD8C","n":38,"a":1597160699000,"p":112},{"i":"37i9dQZEVXbMnf7ONzeQWM","n":21,"a":0,"p":100},{"i":"37i9dQZF1DX4Pso0u1C9Qx","n":49,"a":1596646527000,"p":57}],"pp":2171},"80":{"i":"5udMKRhXsXfUlh25wTDAwD","is":"THG012000080","n":"เหมือนเราเคยรักกัน - เพลงประกอบละคร เหมือนเราเคยรักกัน","a":[{"i":"5YmEu8ngufjZCsX7UzW9YF","n":"Neung Apiwat"}],"p":25,"r":"2020-02-27","l":"GMM Grammy PCL.","im":"https://i.scdn.co/image/ab67616d0000b273f45906d21445f55f0cff3f73","ps":[{"i":"37i9dQZF1DWTzbE633ojB8","n":39,"a":1594923414000,"p":57}],"pp":57},"82":{"i":"2A37KgvlLjBgB16hWHQMMd","is":"THG012000082","n":"จุดพักใจ","a":[{"i":"36YKxDJUt8Q0wY0lqXDQBp","n":"มิกค์ ทองระย้า X นิวจิ๋ว"}],"p":23,"r":"2020-02-26","l":"GMM Grammy PCL.","im":"https://i.scdn.co/image/ab67616d0000b273e2ffb19672c64d9eec33716e","ps":[{"i":"37i9dQZF1DX2wrHNWlb0Eu","n":23,"a":1597160087000,"p":153}],"pp":153},"83":{"i":"3ojNx9FFSc3vLOD8m6bMQS","is":"THG012000083","n":"เธอทำให้ฉันไม่มีแฟน","a":[{"i":"7IeMCKdvAkjYCayJMILk4b","n":"มิน พีชญา X เบล สุพล"}],"p":29,"r":"2020-02-26","l":"GMM Grammy PCL.","im":"https://i.scdn.co/image/ab67616d0000b273e2ffb19672c64d9eec33716e","ps":[{"i":"37i9dQZF1DX2wrHNWlb0Eu","n":22,"a":1597160087000,"p":155},{"i":"37i9dQZF1DWTlbUjNA5MKD","n":26,"a":1597161200000,"p":89},{"i":"37i9dQZF1DX4Pso0u1C9Qx","n":74,"a":1596646527000,"p":44}],"pp":288},"84":{"i":"4IMEDWLCBVGaxsDRLj7ydB","is":"THG012000084","n":"มองเห็นแต่ไม่ได้ยิน","a":[{"i":"37xeI7tCEVwv4BDvrt2PRg","n":"อ๋อม อรรคพันธ์ X กวาง ABnormal"}],"p":13,"r":"2020-02-26","l":"GMM Grammy PCL.","im":"https://i.scdn.co/image/ab67616d0000b273e2ffb19672c64d9eec33716e","ps":[{"i":"37i9dQZF1DWTlbUjNA5MKD","n":24,"a":1597161200000,"p":91}],"pp":91},"93":{"i":"2ABZ6vPw572OPdWdtmskTz","is":"THG012000093","n":"เป็นหยังยังฮักอยู่","a":[{"i":"2YMBbWgfnIjPCtn7ZM2acz","n":"มีนตรา อินทิรา"}],"p":23,"r":"2020-03-03","l":"GMM Grammy PCL.","im":"https://i.scdn.co/image/ab67616d0000b273045d2595a69315d781778a80","ps":[{"i":"37i9dQZF1DXaMYpIMHCml5","n":10,"a":1594751814000,"p":102}],"pp":102},"07":{"i":"2a9VymXQKJj0RCaDN7IdCp","is":"THG012000007","n":"ย่านรถไฟชนกัน","a":[{"i":"0su6At3TbDiuIxJZt9w4eO","n":"เบลล์ นิภาดา"}],"p":36,"r":"2020-01-17","l":"GMM Grammy PCL.","im":"https://i.scdn.co/image/ab67616d0000b273208e6e72fc302626120b2984","ps":[{"i":"37i9dQZF1DXasWh6Blli1c","n":12,"a":1597164132000,"p":102}],"pp":102},"09":{"i":"7bTzluWUvBbD8ucKeSNafz","is":"THG012000009","n":"Beside You - เพลงประกอบซีรีส์ Angel Beside Me เทวดาท่าจะรัก","a":[{"i":"5YmEu8ngufjZCsX7UzW9YF","n":"Neung Apiwat"}],"p":22,"r":"2020-02-12","l":"GMM Grammy PCL.","im":"https://i.scdn.co/image/ab67616d0000b273eceee86e22c8a89883d3b606","ps":[{"i":"37i9dQZF1DWTzbE633ojB8","n":32,"a":1594923414000,"p":62}],"pp":62},"00":{"i":"1FSuKqdbMj0l8jIItYZkvw","is":"THG012000000","n":"เชื่อได้มั้ย? - เพลงประกอบละคร นางสาว 18 มงกุฎ","a":[{"i":"0F2sO0QaLK1iakw7sR80xB","n":"Kacha Nontanun"},{"i":"6TBVRWjGKSLCZwhqSQ03pK","n":"Faye Fang Kaew"}],"p":35,"r":"2020-01-15","l":"GMM Grammy PCL.","im":"https://i.scdn.co/image/ab67616d0000b273a5735dcb918b5cd108ae08da","ps":[{"i":"37i9dQZF1DWZRLdKC8qik7","n":41,"a":1597160900000,"p":81},{"i":"37i9dQZF1DWTzbE633ojB8","n":36,"a":1594923414000,"p":59}],"pp":140}},"s":[]}