{"d":{"500971":{"i":"2yCLbfLmrBwhHrwrxSvuZH","is":"PLB381500971","n":"Nieprawda (Gromee Remix)","a":[{"i":"7008bv4QLo6eziuxszbjqO","n":"Ania Dabrowska"}],"p":48,"r":"2015-06-14","l":"Sony Music Entertainment","im":"https://i.scdn.co/image/ab67616d0000b2739758df3f60feac30463e3f4a","ps":[{"i":"37i9dQZF1DX55gJY7DK9p6","n":58,"a":1597328891000,"p":103},{"i":"37i9dQZF1DWVljVEn3yRPI","n":77,"a":1596794644000,"p":74}],"pp":177},"501027":{"i":"4vlcTHpj4rGBPHGrA1wf2l","is":"PLB381501027","n":"W Dobrą Stronę","a":[{"i":"6EB8VE9f7Ut6NOgviN6gDW","n":"Dawid Podsiadło"}],"p":54,"r":"2015-11-02","l":"Sony Music Entertainment","im":"https://i.scdn.co/image/ab67616d0000b2730402b696ff17a7fd1af764f6","ps":[{"i":"37i9dQZF1DWVljVEn3yRPI","n":58,"a":1596794644000,"p":90},{"i":"37i9dQZF1DX55gJY7DK9p6","n":76,"a":1597328891000,"p":86}],"pp":176},"501107":{"i":"1zBK0FGAcAGCxAxO6jC680","is":"PLB381501107","n":"Color Of Your Life","a":[{"i":"4YT4KZPvKUyqgSgtXAJeS4","n":"Michal Szpak"}],"p":40,"r":"2015-11-13","l":"Sony Music Entertainment","im":"https://i.scdn.co/image/ab67616d0000b2730cd2fb38bbd7f6dfa89f573a","ps":[{"i":"37i9dQZF1DX55gJY7DK9p6","n":41,"a":1597328891000,"p":123}],"pp":123},"600008":{"i":"5xIwk3q4x3ptb6oedWlKf0","is":"PLB381600008","n":"W Glowie","a":[{"i":"7008bv4QLo6eziuxszbjqO","n":"Ania Dabrowska"}],"p":45,"r":"2016-03-04","l":"Sony Music Entertainment","im":"https://i.scdn.co/image/ab67616d0000b2735c024b91c89e0fcf9da57df5","ps":[{"i":"37i9dQZF1DX55gJY7DK9p6","n":51,"a":1597328891000,"p":111}],"pp":111},"600473":{"i":"4V0GI9XBe64RMMiVIVjkBD","is":"PLB381600473","n":"Fearless (feat. May-Britt Scheffer)","a":[{"i":"2oRTLExi1ct74cVtfAwfhV","n":"Gromee"},{"i":"7htwVddNAtE4ZpEC1JhQQT","n":"May-Britt Scheffer"}],"p":40,"r":"2018-03-16","l":"Sony Music Entertainment","im":"https://i.scdn.co/image/ab67616d0000b273547d95167f5fe76df66d5858","ps":[{"i":"37i9dQZF1DX55gJY7DK9p6","n":44,"a":1597328891000,"p":119}],"pp":119},"600816":{"i":"3hElIRa4dB7ZJpWJ3gx04i","is":"PLB381600816","n":"Pod Wiatr","a":[{"i":"2JN7EU0IQBx2cWaHh23Mfm","n":"Grzegorz Hyzy"}],"p":44,"r":"2017-06-09","l":"Sony Music Entertainment","im":"https://i.scdn.co/image/ab67616d0000b27387b6d9997ed9f1e72dba428b","ps":[{"i":"37i9dQZF1DX55gJY7DK9p6","n":52,"a":1597328891000,"p":110}],"pp":110},"601373":{"i":"5MVK9Up4ORQdmOdBuk0MIy","is":"PLB381601373","n":"Porady Na Zdrady [Dreszcze]","a":[{"i":"7008bv4QLo6eziuxszbjqO","n":"Ania Dabrowska"}],"p":50,"r":"2017-01-03","l":"Sony Music Entertainment","im":"https://i.scdn.co/image/ab67616d0000b27379847c6b936d28f6603d44d7","ps":[{"i":"37i9dQZF1DWVljVEn3yRPI","n":94,"a":1596794644000,"p":63}],"pp":63},"601461":{"i":"12BwVTLEvpQREU9mmb8H3C","is":"PLB381601461","n":"O Pani!","a":[{"i":"2JN7EU0IQBx2cWaHh23Mfm","n":"Grzegorz Hyzy"}],"p":50,"r":"2017-06-09","l":"Sony Music Entertainment","im":"https://i.scdn.co/image/ab67616d0000b27387b6d9997ed9f1e72dba428b","ps":[{"i":"37i9dQZF1DWVljVEn3yRPI","n":75,"a":1596794644000,"p":76}],"pp":76},"700455":{"i":"76rZUnOHbjsmCEJOLH0OKd","is":"PLB381700455","n":"Blue Suede Shoes","a":[{"i":"1lmjruOcvyQRZNIKUOlf68","n":"Komodo"}],"p":47,"r":"2017-06-09","l":"Sony Music Entertainment","im":"https://i.scdn.co/image/ab67616d0000b273ec92482a4841a827711bfe95","ps":[{"i":"37i9dQZF1DWVUxkQFrGCkK","n":95,"a":1595206335000,"p":143}],"pp":143},"700804":{"i":"4SDTgdnpGs2CH27ECddcAu","is":"PLB381700804","n":"Z Tobą Nie Umiem Wygrać","a":[{"i":"7008bv4QLo6eziuxszbjqO","n":"Ania Dabrowska"}],"p":54,"r":"2017-10-11","l":"Sony Music Entertainment","im":"https://i.scdn.co/image/ab67616d0000b273e2c38a3025d6cb5b0ac3cd86","ps":[{"i":"37i9dQZF1DWVljVEn3yRPI","n":49,"a":1596794644000,"p":99}],"pp":99},"800220":{"i":"4pzE97EZMDxnqO88y3YxAm","is":"PLB381800220","n":"Małomiasteczkowy","a":[{"i":"6EB8VE9f7Ut6NOgviN6gDW","n":"Dawid Podsiadło"}],"p":53,"r":"2018-06-06","l":"Sony Music Entertainment","im":"https://i.scdn.co/image/ab67616d0000b273167bd3f5f63194ef632cd0d3","ps":[{"i":"37i9dQZF1DWVljVEn3yRPI","n":40,"a":1596794644000,"p":108}],"pp":108},"800255":{"i":"3pe05XBTPu2wpWwkVPzuUX","is":"PLB381800255","n":"Trofea","a":[{"i":"6EB8VE9f7Ut6NOgviN6gDW","n":"Dawid Podsiadło"}],"p":61,"r":"2018-10-19","l":"Sony Music Entertainment","im":"https://i.scdn.co/image/ab67616d0000b273c4aa14d6f01b64808cf9ae31","ps":[{"i":"37i9dQZF1DX55gJY7DK9p6","n":14,"a":1597328891000,"p":161},{"i":"37i9dQZF1DWVljVEn3yRPI","n":20,"a":1596794644000,"p":132}],"pp":293},"800409":{"i":"0Ha2AZQ1cHCxycIpmLyKeg","is":"PLB381800409","n":"Superman","a":[{"i":"0WDJa0qnagyOnMaiD26wht","n":"Kubi Producent"},{"i":"0QR764k0D36npmTMWx5bft","n":"Żabson"},{"i":"5CkZIA3WpaEFxp0wSjMzRI","n":"Young Multi"}],"p":49,"r":"2018-07-13","l":"Sony Music Entertainment","im":"https://i.scdn.co/image/ab67616d0000b2733cc6acb12f9e21d0217fbfa8","ps":[{"i":"37i9dQZF1DWY3UKS6jvnxr","n":96,"a":1596787174000,"p":136}],"pp":136},"800584":{"i":"23OHZTgES84qQNMH4UOqn5","is":"PLB381800584","n":"Serce Nie Sługa","a":[{"i":"7008bv4QLo6eziuxszbjqO","n":"Ania Dabrowska"}],"p":45,"r":"2018-09-07","l":"Sony Music Entertainment","im":"https://i.scdn.co/image/ab67616d0000b2732ee333339d10b7ed5d00934e","ps":[{"i":"37i9dQZF1DWVljVEn3yRPI","n":89,"a":1596794644000,"p":66}],"pp":66},"800675":{"i":"7r3oAZHfnjuPNOsp8S8NvP","is":"PLB381800675","n":"Bad Boy (feat. Beteo, ReTo & Siles)","a":[{"i":"0WDJa0qnagyOnMaiD26wht","n":"Kubi Producent"},{"i":"0kh9Gvy9lGZsq84x7I37DC","n":"Beteo"},{"i":"6QfFTZJHFSe9Xyes6DkAli","n":"Reto"},{"i":"3eXp28Gf4fOTq0HH1wK2ul","n":"Siles"}],"p":52,"r":"2018-12-20","l":"Sony Music Entertainment","im":"https://i.scdn.co/image/ab67616d0000b273a111625a1ec3ed94771258da","ps":[{"i":"37i9dQZF1DWXo9v62EXLlM","n":42,"a":1595251674000,"p":186}],"pp":186},"900015":{"i":"12Uxno5gg8fUIggrCnXueg","is":"PLB381900015","n":"Helsinki","a":[{"i":"0tdKRrbItnLj40yUFi23jx","n":"Daria Zawiałow"}],"p":56,"r":"2019-03-08","l":"Sony Music Entertainment","im":"https://i.scdn.co/image/ab67616d0000b2733eefeda40f9a303cc3ddf97d","ps":[{"i":"37i9dQZF1DXakrXW5YU9SI","n":31,"a":1596720597000,"p":267},{"i":"37i9dQZF1DWTnbCPOmjbdB","n":25,"a":1597328997000,"p":208},{"i":"37i9dQZF1DWZiVxbMbEfyo","n":7,"a":1593677725000,"p":48}],"pp":523},"900020":{"i":"1Rn0B4zeGbcttEct0N1XpP","is":"PLB381900020","n":"Hej Hej!","a":[{"i":"0tdKRrbItnLj40yUFi23jx","n":"Daria Zawiałow"}],"p":60,"r":"2019-03-08","l":"Sony Music Entertainment","im":"https://i.scdn.co/image/ab67616d0000b2733eefeda40f9a303cc3ddf97d","ps":[{"i":"37i9dQZF1DX55gJY7DK9p6","n":3,"a":1597328891000,"p":180},{"i":"37i9dQZF1DWVljVEn3yRPI","n":19,"a":1596794644000,"p":133}],"pp":313},"900151":{"i":"1PqD4a8qULq7TNqBYJTGS3","is":"PLB381900151","n":"9 Żyć (feat. Otsochodzi, schafter & PlanBe)","a":[{"i":"0WDJa0qnagyOnMaiD26wht","n":"Kubi Producent"},{"i":"4zvO09rVUIVTeALhs6xLoB","n":"Otsochodzi"},{"i":"2aDaFARm4U9hf5DI9Fhbnh","n":"schafter"},{"i":"7FwxJtVorL07N6kbqmkPr6","n":"PlanBe"}],"p":48,"r":"2019-06-13","l":"Sony Music Entertainment","im":"https://i.scdn.co/image/ab67616d0000b2730ae6a46089b259882bef645a","ps":[{"i":"37i9dQZF1DWXo9v62EXLlM","n":3,"a":1595251674000,"p":275},{"i":"37i9dQZF1DWY3UKS6jvnxr","n":79,"a":1596787174000,"p":162}],"pp":437},"900211":{"i":"0Klx55wDIEuY63orebP17s","is":"PLB381900211","n":"Czy Ty Słyszysz Mnie? (feat. schafter & Ralph Kaminski)","a":[{"i":"0tdKRrbItnLj40yUFi23jx","n":"Daria Zawiałow"},{"i":"2aDaFARm4U9hf5DI9Fhbnh","n":"schafter"},{"i":"7l1IUcuGTEXMuD1aN3wFqw","n":"Ralph Kaminski"}],"p":51,"r":"2019-06-06","l":"Sony Music Entertainment","im":"https://i.scdn.co/image/ab67616d0000b273d1a0dd9a2ecb96cf46d07525","ps":[{"i":"37i9dQZF1DWVljVEn3yRPI","n":65,"a":1596794644000,"p":84}],"pp":84},"900319":{"i":"30OnKqCINi9fRJyQTEZeDz","is":"PLB381900319","n":"Będzie Lepiej","a":[{"i":"7adgheUEf2iOUaJaz0o1YI","n":"Miyo"},{"i":"1silJqJQfrrZNFvWWjAyhh","n":"Tymek"}],"p":66,"r":"2019-08-12","l":"Sony Music Entertainment","im":"https://i.scdn.co/image/ab67616d0000b2732a877813302b10fbcf9bb3eb","ps":[{"i":"37i9dQZEVXbN6itCcaL3Tt","n":41,"a":0,"p":299},{"i":"37i9dQZF1DX55gJY7DK9p6","n":6,"a":1597328891000,"p":174},{"i":"37i9dQZF1DWVljVEn3yRPI","n":1,"a":1596794644000,"p":160}],"pp":633},"900520":{"i":"0YkUyHza80xODergtHM0jN","is":"PLB381900520","n":"Sweet Emotions","a":[{"i":"2oRTLExi1ct74cVtfAwfhV","n":"Gromee"},{"i":"4Q6zYbQ2MrKiEWTGB3yrPv","n":"Jesper Jenset"}],"p":60,"r":"2020-03-20","l":"Sony Music Entertainment","im":"https://i.scdn.co/image/ab67616d0000b273b19037ddd03c3c8902e32b2b","ps":[{"i":"37i9dQZF1DX843Qf4lrFtZ","n":77,"a":1596751260000,"p":753},{"i":"37i9dQZF1DX0u2K70Zsmro","n":61,"a":1596642923000,"p":215},{"i":"37i9dQZF1DX12meDmp2yzx","n":35,"a":1596641273000,"p":183}],"pp":1151},"900801":{"i":"70dd2vDxjZ421lEE9h0m5m","is":"PLB381900801","n":"Snajper","a":[{"i":"5F4kzxLTvnEhhxRhvUHW6o","n":"Sitek"},{"i":"7adgheUEf2iOUaJaz0o1YI","n":"Miyo"}],"p":45,"r":"2020-07-30","l":"Sony Music Entertainment","im":"https://i.scdn.co/image/ab67616d0000b2732b399b17cf61fa38fcf4b57a","ps":[{"i":"37i9dQZF1DX06QJ0dliLsu","n":22,"a":1597064243000,"p":188}],"pp":188}},"s":[]}