{"d":{"300082":{"i":"4xzgVo1zQucUU8CpUNRD9I","is":"USSTT1300082","n":"Drown","a":[{"i":"4UXiNDHAiv8DOSLkp0GbSm","n":"Front Porch Step"}],"p":0,"r":"2013-11-12","l":"Pure Noise Records","im":"https://i.scdn.co/image/ab67616d0000b273ef6fd048924eea403e6042fb","ps":[{"i":"37i9dQZF1DX0rCrO4CFRfM","n":45,"a":1593601525000,"p":498}],"pp":498},"500192":{"i":"19cXEcwR9Z8uuEnxBWHEVe","is":"USSTT1500192","n":"Hands Tied","a":[{"i":"5VKmfBc2pR80IxYoC1gHyH","n":"Like Pacific"},{"i":"7nJcYa3cIWMFGYX34tkkuq","n":"Andrew Neufeld"}],"p":42,"r":"2020-06-25","l":"Pure Noise Records","im":"https://i.scdn.co/image/ab67616d0000b2732d2cf89af7c75664cd8323bd","ps":[{"i":"37i9dQZF1DX3MU5XUozve7","n":7,"a":1596811552000,"p":682},{"i":"37i9dQZF1DX1ewVhAJ17m4","n":28,"a":1596810382000,"p":466}],"pp":1148},"700039":{"i":"1MAnAUtRTzqnviymxYHTAg","is":"USSTT1700039","n":"Bomb Drop","a":[{"i":"20oQv3LStCKCjI9oQ0JNha","n":"Less Than Jake"}],"p":21,"r":"2017-02-03","l":"Pure Noise","im":"https://i.scdn.co/image/ab67616d0000b27309627404a1fa7264de5c44bb","ps":[{"i":"37i9dQZF1DX6F6y6vVLZ8H","n":23,"a":1595973660000,"p":177}],"pp":177},"700097":{"i":"6lDEE2dGyBEHNOGFlFgswu","is":"USSTT1700097","n":"Lula On The Beach","a":[{"i":"0JXDwBs1sEp6UKoAP58UdF","n":"Seaway"}],"p":1,"r":"2017-09-15","l":"Dine Alone Music","im":"https://i.scdn.co/image/ab67616d0000b2731bd1c5e7b7fd94c106be5056","ps":[{"i":"37i9dQZF1DX6ALfRKlHn1t","n":51,"a":1595540709000,"p":545}],"pp":545},"700201":{"i":"4t7xcd1KMNzxKMIsDQolCz","is":"USSTT1700201","n":"Drowned in Gold","a":[{"i":"4WjeQi9wm84lYTIWZ95QoM","n":"Boston Manor"}],"p":11,"r":"2017-12-05","l":"Pure Noise Records","im":"https://i.scdn.co/image/ab67616d0000b273f1a27de93a40e96494cec619","ps":[{"i":"37i9dQZF1DXcDnIr0iKAG8","n":61,"a":1596667143000,"p":271}],"pp":271},"700249":{"i":"4tOTRRJKhLshJyilxChR3r","is":"USSTT1700249","n":"Take Me as You Please","a":[{"i":"6meTcQ79DrfkIuSLPZkpBg","n":"The Story So Far"}],"p":44,"r":"2018-08-20","l":"Pure Noise Records","im":"https://i.scdn.co/image/ab67616d0000b273a05232078e3e4ec115f524e5","ps":[{"i":"37i9dQZF1DWXMJdkLQRrmg","n":27,"a":1595539644000,"p":356}],"pp":356},"800003":{"i":"2R4drpiAYkjcMiYuVN3iWr","is":"USSTT1800003","n":"Halo","a":[{"i":"4WjeQi9wm84lYTIWZ95QoM","n":"Boston Manor"}],"p":36,"r":"2018-09-07","l":"Pure Noise Records","im":"https://i.scdn.co/image/ab67616d0000b2736b090d2f4dff2aca4a1f181b","ps":[{"i":"37i9dQZF1DXcDnIr0iKAG8","n":39,"a":1596667143000,"p":338},{"i":"37i9dQZF1DX2J9h4w9E0Xj","n":56,"a":1595540184000,"p":98},{"i":"37i9dQZF1DX1helbHcrYM1","n":76,"a":1593707877000,"p":70}],"pp":506},"800008":{"i":"02DLxouSNCY7D8CT3K8jvt","is":"USSTT1800008","n":"Bad Machine","a":[{"i":"4WjeQi9wm84lYTIWZ95QoM","n":"Boston Manor"}],"p":11,"r":"2018-08-14","l":"Pure Noise Records","im":"https://i.scdn.co/image/ab67616d0000b2738c58e79decdba97e5b90ba32","ps":[{"i":"37i9dQZF1DXa6YOhGMjjgx","n":93,"a":1590811320000,"p":252}],"pp":252},"800073":{"i":"4oUMGM2qK7t7JlgWHbFUvD","is":"USSTT1800073","n":"Just What I Needed","a":[{"i":"0JXDwBs1sEp6UKoAP58UdF","n":"Seaway"}],"p":26,"r":"2019-04-19","l":"Pure Noise Records","im":"https://i.scdn.co/image/ab67616d0000b273495547d2ffcdeb193b8534c4","ps":[{"i":"37i9dQZF1DXaDzsRodF91I","n":45,"a":1596810348000,"p":291}],"pp":291},"800083":{"i":"4laGwUyRucrLFv1P1eJ435","is":"USSTT1800083","n":"Blur","a":[{"i":"0JXDwBs1sEp6UKoAP58UdF","n":"Seaway"}],"p":41,"r":"2019-04-19","l":"Pure Noise Records","im":"https://i.scdn.co/image/ab67616d0000b273217264c9a06092f49436d666","ps":[{"i":"37i9dQZF1DX0BZrbvIqxCd","n":70,"a":1596809054000,"p":305}],"pp":305}},"s":["9"]}